{
    "79": {
        "hyperparams": {
            "stocks": [
                "AMGN",
                "CSCO",
                "TRV"
            ],
            "start": "2015-01-01",
            "end": "2025-01-01",
            "risk_aversion": 0.1,
            "n_qubits": 11,
            "budget": 1598,
            "log_encoding": true,
            "layers": 10,
            "prices_now": {
                "AMGN": 258.5511779785156,
                "CSCO": 58.409358978271484,
                "TRV": 239.9084930419922
            },
            "assets_to_qubits": {
                "AMGN": [
                    0,
                    1,
                    2
                ],
                "CSCO": [
                    3,
                    4,
                    5,
                    6,
                    7
                ],
                "TRV": [
                    8,
                    9,
                    10
                ]
            },
            "optimizer": "CMAES",
            "lambda_budget": 1000
        },
        "continuous_variables_solution": {
            "weights": {
                "AMGN": 0.3431762809612928,
                "CSCO": 0.45555798119670704,
                "TRV": 0.20126573784200025
            },
            "allocation": {
                "AMGN": 2,
                "CSCO": 14,
                "TRV": 1
            },
            "value": -2274.6752968414535,
            "left_overs": 23.25812222607601
        },
        "continuous_variables_solution_unconstrained": {
            "weights": {
                "AMGN": 0.36942842809228343,
                "CSCO": 0.4545251458557026,
                "TRV": 0.20277951931538185
            },
            "allocation": {
                "AMGN": 2,
                "CSCO": 13,
                "TRV": 1
            },
            "value": -1722.3509477759083,
            "left_overs": 81.66748141366816
        },
        "exact_solution": {
            "smallest_eigenvalues": [
                -0.2100591887226123
            ],
            "smallest_bitstrings": [
                "11001010100"
            ],
            "first_excited_energy": -0.21005901746364525,
            "optimized_portfolio": [
                {
                    "AMGN": 3,
                    "CSCO": 10,
                    "TRV": 1
                }
            ],
            "second_optimized_portfolio": [
                {
                    "AMGN": 0,
                    "CSCO": 15,
                    "TRV": 3
                }
            ],
            "spectrum": [
                9.601789482196269e-17,
                -0.17653755720721664,
                -0.10720702894723969,
                -0.20799158421463085,
                -0.05833807703659935,
                -0.19699913341522807,
                -0.1466068556910256,
                -0.2095149094851518,
                -0.17385132560521177,
                -0.20284314035559303,
                -0.20728548471343894,
                -0.16052429129036325,
                -0.1953029680274055,
                -0.1864182790013858,
                -0.20979887553791532,
                -0.12516117701775065,
                -0.10488679693811243,
                -0.20765148645579223,
                -0.17520739250010536,
                -0.20221907790186713,
                -0.14478165737584364,
                -0.20966984506139033,
                -0.19616400222775188,
                -0.18529918481469812,
                -0.20689352679045458,
                -0.16211245504656643,
                -0.20344124405179193,
                -0.0829071581954618,
                -0.20990194861813904,
                -0.1272443702128589,
                -0.1875114129237649,
                -0.029100818747349173,
                -0.056933679808050225,
                -0.19658480376464305,
                -0.14569749230094353,
                -0.20959561346484512,
                -0.10605014864965523,
                -0.20782477139347771,
                -0.17587571069989466,
                -0.2018973298373464,
                -0.19486272233953805,
                -0.1869680955992314,
                -0.20985366134374828,
                -0.12620602369567321,
                -0.20709275485949225,
                -0.1613216230178798,
                -0.2031454416457837,
                -0.08162129740671151,
                -0.14385934760273983,
                -0.2097376009120661,
                -0.19573672546670245,
                -0.1858619728665222,
                -0.17453259928242976,
                -0.20253434990507943,
                -0.20747172605128683,
                -0.1597204696127445,
                -0.2099437255334275,
                -0.12827620469191248,
                -0.18804821912245928,
                -0.030627680493467795,
                -0.20373053573352368,
                -0.08418650643534994,
                -0.16289677551146156,
                0.0324002734018856,
                -0.029589410096170134,
                -0.18768375079028904,
                -0.1275748308576452,
                -0.20991616924430073,
                -0.08331668305230178,
                -0.2035345227551391,
                -0.16236385346074178,
                -0.20682869012693775,
                -0.18547959726287966,
                -0.1960281916707068,
                -0.2096921465057947,
                -0.14448773143180407,
                -0.20232043482362716,
                -0.17499252482199834,
                -0.20759473217342267,
                -0.10451381128478676,
                -0.12549564340943303,
                -0.20981711508043815,
                -0.18659463023646317,
                -0.19516309695355102,
                -0.1607796995214949,
                -0.20722466896249278,
                -0.20294043546062868,
                -0.17363239888052553,
                -0.20954120280857952,
                -0.14631690706395542,
                -0.1968673084931044,
                -0.057889996857316106,
                -0.20793881894846522,
                -0.10683801567421353,
                -0.17632667126428608,
                0.0005271496443250993,
                -0.08203280888807804,
                -0.20324071581007236,
                -0.1615750129932515,
                -0.20702991651973618,
                -0.12653847356293635,
                -0.20986987899187673,
                -0.18714242710643947,
                -0.19472082824168915,
                -0.20200069938298842,
                -0.1756628506163248,
                -0.20777002773878034,
                -0.10567916652080683,
                -0.20961992666464213,
                -0.1454055720460273,
                -0.1964510024483178,
                -0.05648363380420027,
                -0.15997790866815215,
                -0.207412943028152,
                -0.20263367730462128,
                -0.17431570468193466,
                -0.18604035579060624,
                -0.19559888694846497,
                -0.20975787309536292,
                -0.1435633960343483,
                -0.20810109291048234,
                -0.1079903458032774,
                -0.17698397384901995,
                -0.0011202069404351667,
                -0.1972770969006376,
                -0.05928984035094781,
                -0.1472217235562936,
                0.06651855470697425,
                -0.015075347586530596,
                -0.18239129656071168,
                -0.11767157244896992,
                -0.20923451931420545,
                -0.07110802258601848,
                -0.20054747065761414,
                -0.1547659971292082,
                -0.2084524424049308,
                -0.17994610467179156,
                -0.19971630934705287,
                -0.2087694588917665,
                -0.15278665475408937,
                -0.19909234468454534,
                -0.18098604527422776,
                -0.20897744716277666,
                -0.1151181375765819,
                -0.115471862911289,
                -0.20901494356546668,
                -0.18118165413204357,
                -0.1989717302660024,
                -0.15306132119838844,
                -0.20872789982884535,
                -0.19983286162382724,
                -0.1797464347091322,
                -0.20849800883865144,
                -0.1544953252268746,
                -0.2004349203741475,
                -0.0706792217752662,
                -0.20920102785280043,
                -0.11732183715286298,
                -0.18219968622976346,
                -0.014567478841777214,
                -0.06976388694840013,
                -0.200193402429368,
                -0.15391689526459612,
                -0.2085934076661624,
                -0.11657495371429441,
                -0.20912796784969953,
                -0.18178971153200263,
                -0.198589721732076,
                -0.19871235446205848,
                -0.18159611682289167,
                -0.20909248819554416,
                -0.11622323889153668,
                -0.208636984388686,
                -0.15364424128024007,
                -0.20007886573082861,
                -0.0693331094256002,
                -0.15219927108543208,
                -0.2088559149980913,
                -0.19946584437097165,
                -0.18036948185223317,
                -0.18056712050324708,
                -0.19934726147884685,
                -0.20889544257905202,
                -0.151922575929318,
                -0.2093030537747182,
                -0.1184139199509984,
                -0.1827967411101485,
                -0.016154588506699045,
                -0.20078446090474786,
                -0.07201881813880585,
                -0.15533989419686495,
                0.049178769218754304,
                -0.04354218751208985,
                -0.19241491987003956,
                -0.1369168041518964,
                -0.21003653397446753,
                -0.09496405841635056,
                -0.2059602896796237,
                -0.1694004246619873,
                -0.20464365261845313,
                -0.19045180321106808,
                -0.1917787871500662,
                -0.21005354738357507,
                -0.13562752114247872,
                -0.2049872382749724,
                -0.16843771746593886,
                -0.2056507303956347,
                -0.09334819795906674,
                -0.13495813834042636,
                -0.21005800089950805,
                -0.19144632071670592,
                -0.1907931778587744,
                -0.1679367922507753,
                -0.20516015235886428,
                -0.20548672363922849,
                -0.16695707722086975,
                -0.21002310845754096,
                -0.13757720030603135,
                -0.19273840816142462,
                -0.044539483185293244,
                -0.20611532166016583,
                -0.09579290552286238,
                -0.16989236777782507,
                0.01618306696954606,
                -0.0937404455726103,
                -0.2057267438432021,
                -0.16867184542789632,
                -0.2049051399574729,
                -0.13594070813883768,
                -0.21005050475418532,
                -0.19193385736192065,
                -0.19029064929582137,
                -0.20472775689727513,
                -0.16916829676539813,
                -0.20588627976386448,
                -0.09457380636481025,
                -0.21004158148003782,
                -0.1366056150988385,
                -0.19226185158638787,
                -0.04307287032156833,
                -0.16719526022113687,
                -0.2054086848634043,
                -0.2052402241333487,
                -0.16770064121224326,
                -0.19095230501247382,
                -0.1912892261728195,
                -0.21005901746364525,
                -0.13464292978218054,
                -0.20633784266037744,
                -0.09700548195932668,
                -0.1706099170541914,
                0.014475464499287152,
                -0.19320844343857993,
                -0.04599957278008322,
                -0.1385422633025941,
                0.08441963016277912,
                -0.1839118407199809,
                -0.1971702459993791,
                -0.20947929381927965,
                -0.14698469654952853,
                -0.20143012985251105,
                -0.17681203403502227,
                -0.20805933256120973,
                -0.1076882334044432,
                -0.1987520225673881,
                -0.06446468232586056,
                -0.1505466044981641,
                0.059493745336283974,
                -0.17938387647139098,
                -0.007220031780093878,
                -0.1122402065041283,
                0.13567664924622908,
                -0.2092930680702006,
                -0.14877860460308534,
                -0.1979740873570318,
                -0.06170661875960484,
                -0.2083681404155688,
                -0.10997717464548684,
                -0.17811090879326136,
                -0.0039669367647334995,
                -0.1522886410306326,
                0.05577158866241497,
                -0.06719677973716094,
                0.2166164658928624,
                -0.11447727367676458,
                0.13145946355357893,
                -0.01044715902599225,
                0.31124259594547277,
                -0.2010927360587077,
                -0.17746470767776074,
                -0.20821697254943328,
                -0.1088359405639367,
                -0.20938941693178859,
                -0.14788488696850507,
                -0.19757540283143998,
                -0.0603178683044755,
                -0.18001062925785527,
                -0.008836846165781538,
                -0.11336199045531878,
                0.13356480516652172,
                -0.15142087295762957,
                0.057629416010386264,
                -0.06583398158621898,
                0.2189693215467065,
                -0.20851283247075375,
                -0.11111193191049518,
                -0.1787506336677933,
                -0.005596725981099511,
                -0.19836629587485863,
                -0.0630888920558221,
                -0.1496658457271049,
                0.061364566515503816,
                -0.11558604396492811,
                0.12936063666067305,
                -0.012050958132321215,
                0.3086487423078258,
                -0.06855306456271523,
                0.2142701254967161,
                0.05392027553320847,
                0.41249648738033295,
                -0.1936248586316292,
                -0.1884400472227606,
                -0.20997070348289565,
                -0.12903288905597263,
                -0.20653234365888698,
                -0.1634710309398044,
                -0.20393993803401506,
                -0.08512562142224822,
                -0.19050389950139504,
                -0.037773338267076476,
                -0.13307687126705708,
                0.09540670096981035,
                -0.16652494840038,
                0.024082117967397076,
                -0.09015966794728461,
                0.1762004109736827,
                -0.21002552158368837,
                -0.13106783985719522,
                -0.18948493195452226,
                -0.034774244158450554,
                -0.20448978951919936,
                -0.08765560504123157,
                -0.16501094877776556,
                0.027576242982416007,
                -0.13505991956675228,
                0.09144353501480271,
                -0.040746446277899015,
                0.26151002612062146,
                -0.0926377463221301,
                0.1717422167155902,
                0.02061398076233321,
                0.3607469635056655,
                -0.20631547269162281,
                -0.16424422698214125,
                -0.20421810067297747,
                -0.0863938506548603,
                -0.21000134934346065,
                -0.1300536017207253,
                -0.18896572658940763,
                -0.033264973614404,
                -0.16727221032253717,
                0.0223447955648978,
                -0.09140196051239727,
                0.17396805954961397,
                -0.13407164861074747,
                0.09342186395390883,
                -0.039263145852218934,
                0.2639833826066578,
                -0.20475499981948386,
                -0.08891087977842879,
                -0.1657711915486118,
                0.025825936793326166,
                -0.18999765855247305,
                -0.036277034686541754,
                -0.13207559867488375,
                0.09739803487356866,
                -0.09386701210861195,
                0.16952289578921817,
                0.018889686852442116,
                0.35803261667998765,
                -0.04222322626381092,
                0.2590431921043092,
                0.08947172745766446,
                0.46649116981314953,
                -0.1890489922229085,
                -0.1930857891891098,
                -0.2100056412099845,
                -0.13828943540728267,
                -0.20426187930778048,
                -0.17042217507778046,
                -0.20628027786516212,
                -0.09668757003387995,
                -0.19490860434282772,
                -0.051399653708484705,
                -0.1420923812391621,
                0.07716957967821675,
                -0.17323505576746065,
                0.008150399651146905,
                -0.10148058060907145,
                0.1556578866009624,
                -0.20993993760413482,
                -0.14020386507458893,
                -0.19401015246292175,
                -0.04852107434812951,
                -0.20670960775863298,
                -0.09909703270921572,
                -0.17184157161039162,
                0.01152401019465686,
                -0.14395492443953337,
                0.07332691755786583,
                -0.05425225721464702,
                0.23878260164502374,
                -0.10383815417250766,
                0.15132019581427256,
                0.004802766625159133,
                0.33571413532060684,
                -0.2039847469996673,
                -0.17113511000355047,
                -0.20649817925658126,
                -0.09789553831857062,
                -0.20997602577164487,
                -0.13924988703508218,
                -0.19355120736899267,
                -0.047072063689154106,
                -0.17392206347718972,
                0.006473330890823458,
                -0.10266261922804731,
                0.15348578847743843,
                -0.14302690449886132,
                0.07524499613838409,
                -0.05282920749476247,
                0.24119570815734948,
                -0.20691455915028706,
                -0.1002920489350494,
                -0.1725415556524059,
                0.009833962261792116,
                -0.1944626202374328,
                -0.04996360648771767,
                -0.14115136526747107,
                0.0791006575205923,
                -0.1050071727067477,
                0.14916112139690454,
                0.0031387196147259298,
                0.33306003457581057,
                -0.05566879012000052,
                0.2363760139283628,
                0.07141535670966742,
                0.43921318363086126,
                -0.1976394399215599,
                -0.18323302006666925,
                -0.20937448060888986,
                -0.1192150574573955,
                -0.2082415228789776,
                -0.15595860158516073,
                -0.20103831303637582,
                -0.07300238752907498,
                -0.18553790786792856,
                -0.023585735817393243,
                -0.12350007440214733,
                0.1142051093998474,
                -0.15925355419271747,
                0.0405751233551688,
                -0.0782774683367948,
                0.19730422255544275,
                -0.2095498199089889,
                -0.1213705288419521,
                -0.18439842572742038,
                -0.020466128077075253,
                -0.2017086855951257,
                -0.07565289153031172,
                -0.15761904018870124,
                0.04418976171430698,
                -0.12560362616183818,
                0.1101214412927573,
                -0.026679346671924665,
                0.2847987395837279,
                -0.08087604987291028,
                0.19272552651933356,
                0.036986483642791904,
                0.3863410807669897,
                -0.20808491307234683,
                -0.15679205854222605,
                -0.20137673673185397,
                -0.0743308774969581,
                -0.2094653875827383,
                -0.12029603095185651,
                -0.18381896042364693,
                -0.01889659800210686,
                -0.16006106958109093,
                0.03877754807832878,
                -0.07958001409102108,
                0.19501161860947538,
                -0.1245551050782116,
                0.11216001968111752,
                -0.025135796438971774,
                0.28733234512332917,
                -0.20203415434082705,
                -0.07696842429403541,
                -0.1584395412143542,
                0.04237919776464033,
                -0.18497141068019204,
                -0.02202917650342685,
                -0.12243854580501554,
                0.11625669872784147,
                -0.08216556188242399,
                0.19044596013478987,
                0.035201943873464286,
                0.38356648892207634,
                -0.028216372703779618,
                0.28227166032400286,
                0.10808938807210658,
                0.49433044623118716,
                -0.11395181578858135,
                -0.20884979706089113,
                -0.18033905681962367,
                -0.1994840358743588,
                -0.1518799988753507,
                -0.20890147919837915,
                -0.19932898957141434,
                -0.1805974669594655,
                -0.20829756989158196,
                -0.15564980723454433,
                -0.20091194044862298,
                -0.07251116893530943,
                -0.2093393180717681,
                -0.11881505131510145,
                -0.18301543688765926,
                -0.01673815988130264,
                -0.1790858280316179,
                -0.20021094111566895,
                -0.20858663547868603,
                -0.15395874396653542,
                -0.1985707944328138,
                -0.18181940546277123,
                -0.20913335107699849,
                -0.11662895645534566,
                -0.20158698017259652,
                -0.07516632957243066,
                -0.1573149082089521,
                0.0448587573890098,
                -0.18418550743403392,
                -0.019888349747980618,
                -0.12097518232061188,
                0.11907499209465724,
                -0.15100910338903623,
                -0.20902065122074465,
                -0.19895312789606054,
                -0.18121167255606144,
                -0.17971567825230458,
                -0.199850724699916,
                -0.20872145224919295,
                -0.15310349463869108,
                -0.20943257180999503,
                -0.11989836699722375,
                -0.18360372195581326,
                -0.01831650545118702,
                -0.20125270994066813,
                -0.07384199965272893,
                -0.15648560769981779,
                0.04667811584239333,
                -0.19818198568074968,
                -0.18242066212893537,
                -0.20923957524134862,
                -0.11772524519847635,
                -0.20844534323601427,
                -0.15480751672492904,
                -0.20056468158339175,
                -0.07117384735683732,
                -0.18476078130672255,
                -0.021453680706349527,
                -0.12204548524479941,
                0.117014634129672,
                -0.15813769673391423,
                0.043045912798246724,
                -0.07648414664151384,
                0.200452483565168,
                -0.13360302980043173,
                -0.21005779447950101,
                -0.19076866261829614,
                -0.19147042466151964,
                -0.16692040879619102,
                -0.20549867233796876,
                -0.20514779120619733,
                -0.16797305131022486,
                -0.20998764428483596,
                -0.1388966609675672,
                -0.1933804048303847,
                -0.046536411297845304,
                -0.20641858753365028,
                -0.09745109945838046,
                -0.17087309602998862,
                0.01384740373846711,
                -0.1897564780767006,
                -0.19243837311516726,
                -0.2100356767020094,
                -0.13696456625564135,
                -0.20463064011199325,
                -0.16943603267317514,
                -0.2059715877439487,
                -0.09502397368038604,
                -0.19429645759187286,
                -0.04943258255452658,
                -0.14080277384585216,
                0.07981411801864621,
                -0.17228417906589397,
                0.010456203950892093,
                -0.09985224174444449,
                0.1586411599154146,
                -0.16617003627581764,
                -0.20573836693340147,
                -0.20489245233801726,
                -0.1687077791704413,
                -0.1902658069469513,
                -0.1919576359148374,
                -0.21004997236734008,
                -0.1359887965391594,
                -0.20663235098384647,
                -0.0986549237676573,
                -0.17158189030537427,
                0.012148550196845043,
                -0.19384168379144745,
                -0.047987750324128414,
                -0.13985297035945105,
                0.08175397804081674,
                -0.20436234996286828,
                -0.17015780720343424,
                -0.20619833017948552,
                -0.09624077980517956,
                -0.21001490290581742,
                -0.1379338566463308,
                -0.19291263165994782,
                -0.04507857647667693,
                -0.17297994923161444,
                0.008770378130276433,
                -0.10104304028394112,
                0.15646030791658444,
                -0.14174605833440201,
                0.07788077897041973,
                -0.050870894871805517,
                0.24450896525657506,
                -0.12405806533588304,
                -0.20973443833879724,
                -0.18583450227027407,
                -0.19575787286117655,
                -0.15968084638119756,
                -0.207480718348175,
                -0.20251903294784498,
                -0.17456590174315725,
                -0.20942325035990167,
                -0.14755387747261717,
                -0.1974268159574562,
                -0.05980443354909741,
                -0.20815959609661316,
                -0.10841371878786304,
                -0.1772249098026623,
                -0.0017260215371730698,
                -0.18470179581011464,
                -0.19660529993492004,
                -0.20959179887440188,
                -0.14574229797338759,
                -0.20188136004148985,
                -0.17590836190795572,
                -0.20783311221133327,
                -0.1061071079543201,
                -0.19822236297082402,
                -0.0625801002882589,
                -0.14933948518041218,
                0.062055793399928325,
                -0.1785154873698452,
                -0.004996717161965479,
                -0.11069435622050483,
                0.13857743165882042,
                -0.15887021244344784,
                -0.20766015173347963,
                -0.202203432747078,
                -0.17524036855337483,
                -0.18527138521923936,
                -0.19618482297972345,
                -0.20966635495057068,
                -0.14482678829866347,
                -0.2083131050394172,
                -0.1095572891429665,
                -0.1778734498284305,
                -0.003364621457735921,
                -0.19782784053530578,
                -0.061195518783055666,
                -0.1484499327578973,
                0.06393540307326472,
                -0.20155281079798787,
                -0.17656987772407134,
                -0.2079995957237753,
                -0.10726365561159287,
                -0.2095107660647657,
                -0.14665132976853706,
                -0.19701929965637344,
                -0.058406855055216894,
                -0.17915100987914073,
                -0.006622296052360628,
                -0.1118249074478439,
                0.13645682617060442,
                -0.15022252217996235,
                0.060182701076827855,
                -0.06395816547963992,
                0.22220007951149165,
                -0.14258670916152127,
                -0.20981986545321574,
                -0.19514153783844354,
                -0.18662169124105982,
                -0.1735986860973556,
                -0.20295534113570507,
                -0.20721526431895562,
                -0.160818915624072,
                -0.20999075149509877,
                -0.12967815753902803,
                -0.18877270689158215,
                -0.03270710199664739,
                -0.20411629220932392,
                -0.085927193144018,
                -0.16395999539154252,
                0.029982116132793547,
                -0.19424987473538102,
                -0.1877101605513348,
                -0.2099182688609737,
                -0.1276255487036797,
                -0.20681863454606061,
                -0.16240241765108587,
                -0.2035487775720407,
                -0.0833795535216573,
                -0.18980926378916718,
                -0.03572377611557895,
                -0.13170477395415608,
                0.09813373150535842,
                -0.16549158227333563,
                0.026470413848517293,
                -0.08844883863904637,
                0.17926617712690496,
                -0.17290857482779445,
                -0.2032552967530783,
                -0.20702018660598706,
                -0.16161390433528833,
                -0.1946989433748201,
                -0.18716916343555748,
                -0.2098723044343399,
                -0.1265895192859373,
                -0.2043903094343531,
                -0.08719127065328586,
                -0.16472904317317513,
                0.028223009735106427,
                -0.18929423949789403,
                -0.034218694055667284,
                -0.13069472028873974,
                0.10013384096987046,
                -0.20661060304174994,
                -0.1631844504243024,
                -0.20383577847029843,
                -0.08465661763197577,
                -0.2099577536232588,
                -0.1286550972133197,
                -0.18824467745366336,
                -0.03118901147168616,
                -0.16624759907992318,
                0.02472434213486162,
                -0.08969988346433164,
                0.1770250796654533,
                -0.1327083049107431,
                0.09614014677459257,
                -0.03722233452698085,
                0.2673791411005296,
                -0.20988007469003878,
                -0.14149890390294803,
                -0.1946277398342614,
                -0.050493566112622276,
                -0.20698846986002747,
                -0.10073079780153174,
                -0.17279788454457234,
                0.009212791311325986,
                -0.1452146834177677,
                0.0707122346008923,
                -0.056189476639413274,
                0.23549045176263714,
                -0.10543664300751923,
                0.14836677983796387,
                0.002526815839219326,
                0.33208325060695826,
                -0.1955085168943495,
                -0.05335447674295779,
                -0.14336974796784457,
                0.07453729790179342,
                -0.17417369516070502,
                0.005856847569439336,
                -0.10309667520534979,
                0.1526868744439004,
                -0.058998509094349644,
                0.2307012999437556,
                0.0669131416415813,
                0.4323659676096666,
                -0.0007772470722240451,
                0.326799069981498,
                0.14407265724198642,
                0.5474019931025588,
                -0.2071845776852289,
                -0.10191697298828314,
                -0.1734890261214403,
                0.007531582666722164,
                -0.19507136455237847,
                -0.05192725804794415,
                -0.14243756230312102,
                0.07645954932438676,
                -0.10659689444057968,
                0.14621646715320535,
                0.000871533408059426,
                0.3294379084233484,
                -0.0575972436639456,
                0.2330926242334688,
                0.06880943694922995,
                0.43525231997601677,
                -0.17485188778556518,
                0.004188589946014556,
                -0.10426990055106325,
                0.15052358499615348,
                -0.14429545700788393,
                0.07262152430889332,
                -0.054775218283559954,
                0.23789477221871644,
                -0.002419513210155576,
                0.3241667477226168,
                0.14193536252065014,
                0.544274644362238,
                0.06502336108185545,
                0.4294861319774118,
                0.22831649132227377,
                0.6685322851725203,
                -0.20965489647176522,
                -0.1228305088864986,
                -0.1851809533256596,
                -0.02260356228630542,
                -0.20215248751849815,
                -0.07745159842318251,
                -0.15874029381451776,
                0.04171359968224074,
                -0.12702836268385845,
                0.1073417766750368,
                -0.02878154557932652,
                0.2813416056232206,
                -0.08263951719122475,
                0.18960712770349875,
                0.034545552315068395,
                0.3825452106768108,
                -0.1863027737570474,
                -0.025705515117601264,
                -0.12494239581286506,
                0.11140786953472762,
                -0.16035714756587002,
                0.03811661412615329,
                -0.08005851837705069,
                0.19416825130848037,
                -0.03183158844916795,
                0.27631144594365586,
                0.10330167450259176,
                0.4871977277560188,
                0.031000479570770647,
                0.3770200229233964,
                0.18507199655177722,
                0.6068445607263794,
                -0.20246911798982054,
                -0.07875829579504719,
                -0.1595519578446729,
                0.03991186919603662,
                -0.18574510060289778,
                -0.02415777624440171,
                -0.12388968961528934,
                0.11345064070550112,
                -0.0839202771426853,
                0.18733630765328846,
                0.032769761904312966,
                0.37977936181723304,
                -0.03030982086227411,
                0.2788232710639248,
                0.10531847134143302,
                0.4902045801769489,
                -0.16115585803697435,
                0.03632783946346187,
                -0.08135226120318922,
                0.19188444533796523,
                -0.12598862252565624,
                0.10937157915139267,
                -0.02724677392746686,
                0.2838664382446644,
                0.0292377187702515,
                0.37426720750084663,
                0.18281420787964284,
                0.6035967196848592,
                0.10129139962675535,
                0.48419739938191153,
                0.2738061437555225,
                0.732465168715676,
                -0.2100481281365285,
                -0.13244534898499788,
                -0.19018498914923618,
                -0.03682920681808627,
                -0.20485112125079505,
                -0.0893718407158868,
                -0.16604973175840143,
                0.025182552861230993,
                -0.13640216639878847,
                0.08874636218269744,
                -0.04276615450731638,
                0.25813538517299217,
                -0.09431872347141423,
                0.1687063102840481,
                0.018255540651455866,
                0.35703358708685606,
                -0.19118628812692,
                -0.03981063880247071,
                -0.13443671472338664,
                0.09269194079956036,
                -0.16754606417949558,
                0.02170608795326927,
                -0.09185823964289291,
                0.1731469199314795,
                -0.04569569296764686,
                0.2532257286042046,
                0.0848267638080662,
                0.4595012032605096,
                0.01483097202023779,
                0.3516289020724487,
                0.16429168259603927,
                0.576842632447966,
                -0.2051074904783038,
                -0.09061827708525319,
                -0.16680113464656537,
                0.02344108320036303,
                -0.1906888752288632,
                -0.038323159857556424,
                -0.13344426863683476,
                0.09467445226245724,
                -0.09553922952591917,
                0.16649574354350732,
                0.01654000386284771,
                0.3543279911868016,
                -0.04423417602600391,
                0.25567730375300135,
                0.08678331031971137,
                0.4624478061033618,
                -0.16828451594822322,
                0.019977571578654058,
                -0.0930917239549704,
                0.17092337198538576,
                -0.13542268282324998,
                0.09071590857718279,
                -0.041291639206558914,
                0.2605999620194662,
                0.013128458047268818,
                0.3489363327171785,
                0.1620941403901548,
                0.5736550370370833,
                0.08287673558383865,
                0.45656112074007127,
                0.25078067268754434,
                0.7002180819089223,
                -0.20870037966728844,
                -0.11265438356991075,
                -0.1796156323305309,
                -0.007816632475199743,
                -0.19889256863240592,
                -0.06497007088360872,
                -0.15086957067765133,
                0.05880593181870544,
                -0.1170932720939388,
                0.12649847826602867,
                -0.014235649671864746,
                0.30510911330598334,
                -0.07039902398564196,
                0.21106923228670538,
                0.051396851015906256,
                0.4086181215717507,
                -0.18085797368098244,
                -0.01103910557551987,
                -0.11488679112799088,
                0.1306850842246649,
                -0.15260694521380977,
                0.05508842620319088,
                -0.06769751129726316,
                0.21575086869454219,
                -0.017406195284584067,
                0.29995845222552,
                0.12233787398402615,
                0.5154555413641401,
                0.04773127583597314,
                0.40297243280002104,
                0.2064135993703387,
                0.6374077782080206,
                -0.19926946015367403,
                -0.06633702904248083,
                -0.15174149564511788,
                0.056943940733468035,
                -0.1802400406061068,
                -0.009431107131025124,
                -0.11377382516556969,
                0.13278811473551339,
                -0.07174003707419366,
                0.2087381597083125,
                0.04956080775367909,
                0.40579202054495045,
                -0.015824177953802535,
                0.30253052639427547,
                0.12441492023788978,
                0.5185226424293532,
                -0.15346591391042447,
                0.05323939375091272,
                -0.06905151214978543,
                0.21340680520890684,
                -0.11599327597143771,
                0.1285885361842677,
                -0.012640622298079397,
                0.3076942010515967,
                0.04590826925076576,
                0.4001593723746767,
                0.20409556528562822,
                0.6340996926111595,
                0.12026735350484907,
                0.5123949682062584,
                0.2973929048249929,
                0.7652735459006491,
                -0.06247488174821725,
                -0.19819265099425792,
                -0.14927201673881504,
                -0.20923678391288375,
                -0.1106080118102094,
                -0.2084492801706797,
                -0.17846689648859296,
                -0.2005551620960514,
                -0.19657342168957737,
                -0.1847454477574097,
                -0.20959768653110994,
                -0.122016704090804,
                -0.20782011699479602,
                -0.1581156391279776,
                -0.20190613016857684,
                -0.0764486424365691,
                -0.1474852863600499,
                -0.20943018767463434,
                -0.19739598786975826,
                -0.18358788483501082,
                -0.17717519978168175,
                -0.20124359915651704,
                -0.20814765053658768,
                -0.15646304454304555,
                -0.20973922753343943,
                -0.12413836639001458,
                -0.18587705019490502,
                -0.024523174503089388,
                -0.20254270208388936,
                -0.07906533407018893,
                -0.15974227169429206,
                0.0394881125628556,
                -0.10947036545750682,
                -0.20830170136165582,
                -0.1778242839607824,
                -0.20090261688946032,
                -0.14838188731118115,
                -0.20933672192026093,
                -0.1977975553397442,
                -0.1829993861233098,
                -0.20764662106572163,
                -0.1589322053140641,
                -0.20222766565149453,
                -0.07776023860675352,
                -0.20967170639599414,
                -0.12308078535946379,
                -0.1853144986811554,
                -0.022970564825487375,
                -0.17651964054433514,
                -0.20157810544053123,
                -0.20798712426365396,
                -0.1572925829662958,
                -0.19698794516491072,
                -0.18416990724149715,
                -0.20951717773174805,
                -0.12094613242673172,
                -0.20285122754413226,
                -0.08036391685551106,
                -0.16054582632216585,
                0.03769450264051438,
                -0.18643309036459532,
                -0.026069270985115068,
                -0.12518943522352527,
                0.1109274042940738,
                -0.08709519380334799,
                -0.20436974649807976,
                -0.16467072059540475,
                -0.20619227082520974,
                -0.1306175197800665,
                -0.21001557141387622,
                -0.1892547961933585,
                -0.1928998445967003,
                -0.20323259473852734,
                -0.17296140030682733,
                -0.2070352496425879,
                -0.10101104536907224,
                -0.2098684851478022,
                -0.14172078613573813,
                -0.1947328880823797,
                -0.05083217778694718,
                -0.16312503463055653,
                -0.20662671800087162,
                -0.20381412736283405,
                -0.17156280552050093,
                -0.18820414370686747,
                -0.19382932472690093,
                -0.20995498550020164,
                -0.1398271602040401,
                -0.2074178042868134,
                -0.10337371892629121,
                -0.17433401526961484,
                0.00546308644333747,
                -0.19561047310012109,
                -0.053689879988429,
                -0.14358843061253806,
                0.07408518063114224,
                -0.12960039644762392,
                -0.20998851524927176,
                -0.18873270653555752,
                -0.19336782173359862,
                -0.16390111412232308,
                -0.20641273133595942,
                -0.20409517361019835,
                -0.1708537862856837,
                -0.209815499203454,
                -0.14265786123876936,
                -0.19517493305380268,
                -0.05226428222717626,
                -0.2072297792535054,
                -0.1021956352406441,
                -0.173650960442716,
                0.007136198042642844,
                -0.18766910323599773,
                -0.19428434905558084,
                -0.20991497767050898,
                -0.14077721619804096,
                -0.20352660327226282,
                -0.17226534574411348,
                -0.20683422631135656,
                -0.0998199602186062,
                -0.19603949523537115,
                -0.055108958035006816,
                -0.14451248124621308,
                0.07217107626743062,
                -0.17501055178912703,
                0.003796495100581266,
                -0.10454528340274813,
                0.1500147857488003,
                -0.07506568031534433,
                -0.20156184131109967,
                -0.15725201121568147,
                -0.20799516995768635,
                -0.1208934083382858,
                -0.2095130683681442,
                -0.184141488896808,
                -0.19700814594962554,
                -0.20018365146842232,
                -0.17913406738450136,
                -0.20859711138655063,
                -0.11179451814235142,
                -0.20912494434741602,
                -0.15019885601333716,
                -0.1986001524506017,
                -0.0639210535569428,
                -0.15558580324168952,
                -0.20830909564583017,
                -0.2008857003898532,
                -0.17785598802770283,
                -0.18297031450332743,
                -0.19781710476980222,
                -0.20933196080829308,
                -0.14842574524718055,
                -0.20885915997363902,
                -0.11403668685600016,
                -0.18038617685926525,
                -0.00981068830591487,
                -0.19935723168634545,
                -0.06665825126533341,
                -0.15194599531492264,
                0.05650600227910821,
                -0.11981602355789436,
                -0.20942575095432298,
                -0.18355913787158942,
                -0.19741586199317807,
                -0.15642214333020757,
                -0.20815536929244524,
                -0.20122700711019176,
                -0.17720722890529567,
                -0.20901170375588402,
                -0.15107567701388686,
                -0.19898194302835714,
                -0.06529290422354611,
                -0.2087313864723334,
                -0.11291885407116112,
                -0.17976337326760616,
                -0.008197827235315097,
                -0.1823750148528996,
                -0.19821187029064113,
                -0.20923169396606606,
                -0.14931554267570393,
                -0.20053791719852684,
                -0.17849826955994666,
                -0.2084563450414183,
                -0.11066368944443528,
                -0.1997260059707701,
                -0.06801708217877314,
                -0.1528097984377811,
                0.054652144633186225,
                -0.1810024656932475,
                -0.011417032718498499,
                -0.11514800400577119,
                0.1301904501542586,
                -0.09856342219346145,
                -0.2066163665273515,
                -0.1715281448546783,
                -0.20382808648306783,
                -0.13978034611451431,
                -0.2099567892777579,
                -0.19380681835266683,
                -0.18823025800261825,
                -0.2057202513305464,
                -0.16622744634596107,
                -0.20491210112533553,
                -0.08966628558799891,
                -0.21005073922433726,
                -0.13268142931448285,
                -0.19030433688775356,
                -0.03718201494134486,
                -0.1701029804325944,
                -0.20438305463662143,
                -0.20618126869010384,
                -0.16470833720572836,
                -0.19287668729597438,
                -0.18928025892240527,
                -0.21001672451144593,
                -0.13066728930367674,
                -0.2054151602283269,
                -0.0921494623471707,
                -0.16772056517677786,
                0.021298150002924447,
                -0.19130242607831,
                -0.040160219983488954,
                -0.1346695773356914,
                0.09222564787948459,
                -0.13882348407028333,
                -0.2099899941810101,
                -0.19334498989173504,
                -0.18875849604069106,
                -0.1708187996288454,
                -0.20410880798304118,
                -0.20640205477654144,
                -0.16393905819217164,
                -0.2100580072014398,
                -0.13367875777263943,
                -0.19080663551629967,
                -0.03867437239703174,
                -0.20516688453024812,
                -0.09091112864957124,
                -0.16697725999268218,
                0.023031511231268672,
                -0.19240190556192793,
                -0.18979554159456827,
                -0.21003697524074155,
                -0.13167760338798598,
                -0.20595400325214677,
                -0.1654711356509448,
                -0.2046508214030503,
                -0.08841494460165203,
                -0.1917916950556547,
                -0.04163954413285054,
                -0.13565387446064076,
                0.09025129783914937,
                -0.16845734836768272,
                0.019571312765755824,
                -0.09338127312536545,
                0.17040041137587042,
                -0.20239493158497668,
                -0.1748335488413008,
                -0.20755249071014054,
                -0.10423810523134391,
                -0.20970827373751744,
                -0.14427038981305956,
                -0.19592758243922415,
                -0.05473669495315425,
                -0.17748232698747424,
                -0.002375197882434138,
                -0.10886701457452982,
                0.14199312451193735,
                -0.1479092337393535,
                0.06507440000061904,
                -0.06035566934487947,
                0.2283809758790225,
                -0.20789976639733782,
                -0.10656551460569649,
                -0.17617089158462507,
                0.000916365624567285,
                -0.19676989170634132,
                -0.057559137477204134,
                -0.14610276592631574,
                0.06886099488486881,
                -0.11114254918195857,
                0.13773747015112242,
                -0.0056407931818228015,
                0.31899224257800807,
                -0.06312623450082394,
                0.22363029260534922,
                0.061313774965419676,
                0.4238233203388513,
                -0.20963763076389097,
                -0.14518981423883587,
                -0.19635197323262277,
                -0.05615115286641284,
                -0.20772936463621758,
                -0.10540504641961387,
                -0.17550545646836008,
                0.0025718665848927314,
                -0.14880273590080734,
                0.06319083641334769,
                -0.06174420258792475,
                0.22600238269513762,
                -0.1100080323683093,
                0.13986204603226765,
                -0.004011246390403504,
                0.32161184665058606,
                -0.19718133407754673,
                -0.05896064495296045,
                -0.14700924106779997,
                0.06696445552109412,
                -0.1768298503948304,
                -0.0007326578516204105,
                -0.10771950596945773,
                0.1441306953715597,
                -0.0645017527860714,
                0.221264717956899,
                0.05944322797920884,
                0.420962719077133,
                -0.007263825946751918,
                0.31637915449116183,
                0.13561940920331111,
                0.5350154120056879,
                -0.20713885143624405,
                -0.16113425195120715,
                -0.20307480229315772,
                -0.08131719957877803,
                -0.2098413894749856,
                -0.1259602885831814,
                -0.18683908981657477,
                -0.02720498478443498,
                -0.16426510511447165,
                0.029285245155221126,
                -0.08642818245681194,
                0.1828751792292534,
                -0.13008120682311447,
                0.10134564877785784,
                -0.0333060318568769,
                0.27387383674747157,
                -0.20366312160119504,
                -0.08388565143769786,
                -0.16271263782257533,
                0.032817838723056644,
                -0.18792244247696865,
                -0.030268469414809377,
                -0.12803370752157803,
                0.10537327317171369,
                -0.08894472816556062,
                0.17837851628727303,
                0.025778639939250097,
                0.36885490272413957,
                -0.036317607540607574,
                0.26888214561684654,
                0.09734401447494953,
                0.47829678788946894,
                -0.20989126924281637,
                -0.12700023530644072,
                -0.1873840031671135,
                -0.02873996466018015,
                -0.20337219887795036,
                -0.08260466290645024,
                -0.1619266820149955,
                0.034593859607057825,
                -0.1310952178167419,
                0.09934157749432779,
                -0.03481507340180802,
                0.2713747365482948,
                -0.08768970882703869,
                0.1806235933843906,
                0.027528688638761883,
                0.3715950072452314,
                -0.18845440289897286,
                -0.03179049415142039,
                -0.129060700356559,
                0.10335621705506587,
                -0.16349211451434534,
                0.03104829823058754,
                -0.08516016028805247,
                0.185133262538954,
                -0.03781362091143492,
                0.2663960773647014,
                0.0953529731064316,
                0.47531569387800787,
                0.024035112430959963,
                0.3661213214511577,
                0.17613996133704307,
                0.5939791949466937,
                -0.2050475340616259,
                -0.16826454298006172,
                -0.20559428906538574,
                -0.0930582950162887,
                -0.2100554741627091,
                -0.13539598179471946,
                -0.1916639787007529,
                -0.041251482496488426,
                -0.1711543593788292,
                0.013174380203101412,
                -0.09792824189257032,
                0.16215350837356127,
                -0.1392758636326932,
                0.082929380924994,
                -0.04711149400505535,
                0.2508467627815857,
                -0.2060620867881227,
                -0.09550622587966756,
                -0.1697224075233384,
                0.01658645927026056,
                -0.19262680989503375,
                -0.04419444632584897,
                -0.13734887956188258,
                0.08683649109919324,
                -0.1003242828417745,
                0.15777734890942474,
                0.009788279143494468,
                0.343642928259398,
                -0.05000256522141415,
                0.2459755747612918,
                0.07904825044860739,
                0.4507794096787765,
                -0.21004509263564475,
                -0.1363756674558825,
                -0.19214863085396072,
                -0.042726201483041126,
                -0.2058314243993575,
                -0.09428549736360778,
                -0.1689967119094274,
                0.01830222035522429,
                -0.14022962056906493,
                0.08098556311995003,
                -0.04856028176328089,
                0.24840791571500642,
                -0.09912951433610787,
                0.15996217583894917,
                0.011478077323946888,
                0.3463227830020308,
                -0.19309851150897123,
                -0.04565621266017687,
                -0.13831561377285345,
                0.08487969312543225,
                -0.17044162549436204,
                0.014877177055085117,
                -0.09672047621216665,
                0.164351335762522,
                -0.05143833154978203,
                0.2435497527998524,
                0.07711745576550644,
                0.44785856152563897,
                0.008104998503851405,
                0.34096959306563934,
                0.1555990404519652,
                0.5642166584760121,
                -0.20866888368230957,
                -0.15344267571913625,
                -0.19999403036239413,
                -0.06901481887867045,
                -0.20906601964555577,
                -0.1159633101405736,
                -0.18145291575335787,
                -0.01259720177458227,
                -0.15681456401730157,
                0.04595739716010577,
                -0.074366836085614,
                0.20415813726973442,
                -0.1203252631312473,
                0.1203232037476615,
                -0.01893928271643371,
                0.2974621979696708,
                -0.20070287073474324,
                -0.07170379116889639,
                -0.15514158237598272,
                0.049610504098387076,
                -0.18265678934806456,
                -0.015781206630924024,
                -0.11815724969678049,
                0.12447134122013148,
                -0.07700388490092669,
                0.19954097254613684,
                0.042330289462374354,
                0.39462816623824437,
                -0.022071361203743967,
                0.29235000543575207,
                0.1162010673036469,
                0.5063754552392087,
                -0.20917616052123972,
                -0.11706351771726459,
                -0.18205809010337382,
                -0.014192442320043219,
                -0.20035168800556083,
                -0.07036254297262494,
                -0.15429536671408742,
                0.05144678442045013,
                -0.12139952742909171,
                0.11825887976030627,
                -0.02050857728422097,
                0.29490284542336964,
                -0.07568861562408624,
                0.2018462988946887,
                0.044140587775597206,
                0.39742851961082215,
                -0.1832490081080963,
                -0.017363489278155345,
                -0.1192445006749201,
                0.12239402746307179,
                -0.15598131731305498,
                0.04778070582569301,
                -0.07303855805084906,
                0.20647647585620177,
                -0.023627620580994987,
                0.28980369195056077,
                0.11414978029655898,
                0.5033341164378959,
                0.040526516126878645,
                0.3918343399491039,
                0.19724217215539058,
                0.6243030217236597,
                -0.15443080211596544,
                -0.2085089954000433,
                -0.20040814918356592,
                -0.17873334009101002,
                -0.18215403822640952,
                -0.19835573049076755,
                -0.20919313493290279,
                -0.1496418240668612,
                -0.20902377019226084,
                -0.11555621876608574,
                -0.18122824644604102,
                -0.01200768580199566,
                -0.1998605712388708,
                -0.06851651554136029,
                -0.1531267956747387,
                0.05397027067041897,
                -0.1996884219407708,
                -0.17999374676490407,
                -0.20877933531387113,
                -0.11333165528147582,
                -0.20896844131670772,
                -0.15139726396567504,
                -0.19912110383547899,
                -0.06579692053614647,
                -0.18243678468204272,
                -0.015196344565984862,
                -0.11775481806707705,
                0.12523863750963823,
                -0.15483036464220293,
                0.050286582782082326,
                -0.07121014477538047,
                0.20965981987734528,
                -0.1815498935940527,
                -0.1987416533313785,
                -0.20908402409721794,
                -0.1505227804531433,
                -0.20005152146395153,
                -0.17936677972142467,
                -0.20864740141819407,
                -0.11220965537149799,
                -0.20022057454993503,
                -0.0698665806243406,
                -0.1539818302333079,
                0.052125175796369425,
                -0.1818357654706041,
                -0.01360526587281882,
                -0.11665876867788796,
                0.12732474462276042,
                -0.20884638299647834,
                -0.15226527095982834,
                -0.1994940783833088,
                -0.06715995954464016,
                -0.208904793479748,
                -0.11444717833743767,
                -0.18061423758925305,
                -0.010403614384150073,
                -0.15567238679185635,
                0.04845450378686124,
                -0.07254719586004403,
                0.20733271400626696,
                -0.11884435481165126,
                0.12315904494651098,
                -0.016780909734624355,
                0.3009755112479178,
                -0.16911291808056486,
                -0.20474789472574956,
                -0.20586865691849016,
                -0.16575063074345286,
                -0.1922253500933329,
                -0.18998382551812915,
                -0.21004283849094227,
                -0.1320483102572491,
                -0.20574474588111047,
                -0.09383397363028434,
                -0.16872761204751735,
                0.018936170805490135,
                -0.19197074195999064,
                -0.04218346476679864,
                -0.13601535599409573,
                0.089524933315556,
                -0.20538997373409051,
                -0.16725208040760314,
                -0.2052592782392424,
                -0.0913683791422768,
                -0.2100591887226123,
                -0.1340447927851095,
                -0.19099024217663596,
                -0.03922283929238207,
                -0.17017716269614389,
                0.015506502080897254,
                -0.09627358419322937,
                0.16516309789914252,
                -0.1379599368176842,
                0.08560023617379545,
                -0.045118104630932604,
                0.25419508752816206,
                -0.1917417283623432,
                -0.19049027085019993,
                -0.21005425038934047,
                -0.1330497888170276,
                -0.20563255202601852,
                -0.16650459271576337,
                -0.20500682336608905,
                -0.09012585898839434,
                -0.1924512547000129,
                -0.043654038176889176,
                -0.13699089946836865,
                0.08755933077832959,
                -0.16945564025382912,
                0.017218082730106162,
                -0.09505703217291087,
                0.1673697062178809,
                -0.21005764883152944,
                -0.1350333174525316,
                -0.19148373481334302,
                -0.040706395483196156,
                -0.20550525467354866,
                -0.09260441963545063,
                -0.1679930891224424,
                0.020660755212080183,
                -0.1389224548681396,
                0.08364766272559088,
                -0.046575650930158946,
                0.25174748804101915,
                -0.09748361650490361,
                0.16296301129207308,
                0.01380144206906722,
                0.3500010932647785,
                -0.16205250264215584,
                -0.2069090876358674,
                -0.20341904560578455,
                -0.17252262801576687,
                -0.18747033670827573,
                -0.19445042058928275,
                -0.2098986292748675,
                -0.14112570977612882,
                -0.2076649013264007,
                -0.10497573958962444,
                -0.17525857258368194,
                0.0031835990484215147,
                -0.19619629991182058,
                -0.05563063357554336,
                -0.14485171919766948,
                0.07146695850596256,
                -0.20281984060365416,
                -0.17390355641787922,
                -0.20729994957180703,
                -0.10263066008722724,
                -0.20979445779947797,
                -0.14300167122796192,
                -0.19533631581857686,
                -0.05279052281423394,
                -0.17658761780345905,
                -0.000125565494955822,
                -0.1072948453098673,
                0.144920223371931,
                -0.14667579487606472,
                0.06766276518642197,
                -0.058444768918301,
                0.23164680932751436,
                -0.1869264535956101,
                -0.19489660475544257,
                -0.2098497798806376,
                -0.14206692733438392,
                -0.20312267937145131,
                -0.1732163288996513,
                -0.20710775504222873,
                -0.101448399899323,
                -0.19661655828936947,
                -0.05704095318489581,
                -0.14576700857150213,
                0.06956160943210198,
                -0.17592634655382744,
                0.0015257646097981271,
                -0.10613854417695295,
                0.1470665815268334,
                -0.20973265890432807,
                -0.14392993728006725,
                -0.19576954962675747,
                -0.054213820640611726,
                -0.20748566708510716,
                -0.10380644208581621,
                -0.17458430640608846,
                0.004847927258112585,
                -0.14757806546962354,
                0.06577043846039321,
                -0.059842068109155974,
                0.22925945613868204,
                -0.10844463033419888,
                0.14278038327981393,
                -0.0017703785868036091,
                0.32520765732406726,
                -0.17561204840854874,
                -0.20202541663796497,
                -0.20775698309450014,
                -0.15841734823780346,
                -0.19641907835666653,
                -0.1849559452433117,
                -0.20962576255167328,
                -0.12240962547168752,
                -0.20326330368316675,
                -0.08213092070576145,
                -0.1616353646597847,
                0.03525002965605423,
                -0.18718389720788664,
                -0.028175008930552217,
                -0.12661770588398372,
                0.10814419528831345,
                -0.207398821234147,
                -0.16003931862706128,
                -0.2026573212137051,
                -0.07954481233506941,
                -0.2097626339859075,
                -0.12452662852783314,
                -0.18608288280491359,
                -0.02509386985676593,
                -0.16320541911158448,
                0.03169985841916796,
                -0.08469103446410975,
                0.1859672613534062,
                -0.12868279021627788,
                0.1040989960040668,
                -0.03123015165795191,
                0.2773046547436908,
                -0.19599571783396336,
                -0.18552265154628045,
                -0.20969743555849882,
                -0.1234713648271652,
                -0.20758113936509395,
                -0.15923157109812147,
                -0.20234460632267626,
                -0.07824203256253232,
                -0.18772466357099726,
                -0.029705835380372223,
                -0.1276535027085006,
                0.10611834005954188,
                -0.16242364635747106,
                0.03347168871032427,
                -0.08341423244808335,
                0.1882341189226614,
                -0.2098213526425039,
                -0.12557541133256112,
                -0.18663663380294815,
                -0.026637683923194416,
                -0.20296355610722341,
                -0.08084111083941223,
                -0.16084058559592604,
                0.03703486962922213,
                -0.12970555470124656,
                0.10208617687769297,
                -0.032747944032354384,
                0.2747968100130552,
                -0.08596131303533744,
                0.18370692928079718,
                0.029934552525956625,
                0.37535581937209966,
                -0.20636727000899002,
                -0.09716631115619759,
                -0.1707050411644921,
                0.01424892083573293,
                -0.19327071819337857,
                -0.046193257971829535,
                -0.13867023884961782,
                0.08416022541858098,
                -0.10194909181825401,
                0.1547976151660801,
                0.007486009348173244,
                0.3399857271313158,
                -0.05196610423538747,
                0.24265710777438823,
                0.07640724908964247,
                0.44678347347345515,
                -0.17211931952813933,
                0.010854509020172732,
                -0.0995706564726217,
                0.15915617810808858,
                -0.14057955074507772,
                0.08027078052997239,
                -0.04909263659580765,
                0.24751070194886277,
                0.004143479279127593,
                0.3346630780891938,
                0.15046502478095802,
                0.5567376410376897,
                0.07256968865645533,
                0.4409657957313906,
                0.2378294878521007,
                0.6819786142869364,
                -0.193733576793085,
                -0.04764618389451991,
                -0.13962813118527545,
                0.08221226606802415,
                -0.17141541665014887,
                0.012548478178573198,
                -0.09837172030462696,
                0.1613451799470494,
                -0.05339310483369886,
                0.2402400460992117,
                0.07448521757708049,
                0.443871382397548,
                0.005811493199422353,
                0.3373211506598979,
                0.15262806847761506,
                0.5598907415698794,
                -0.14152449355825322,
                0.07833577282493151,
                -0.05053261208005452,
                0.24508066248355248,
                -0.10076311567697718,
                0.15697365446470685,
                0.00916701736860384,
                0.34265679709693586,
                0.0706606748132122,
                0.43806672601016416,
                0.2354254455433684,
                0.6785845182164579,
                0.14830849657398626,
                0.5535910580082927,
                0.33201152194194916,
                0.8130471069346299,
                -0.20117299371028613,
                -0.07352881799878216,
                -0.1562891565515211,
                0.04710802285227142,
                -0.1834656377610318,
                -0.017944960429468717,
                -0.11964354999847784,
                0.12163013200909195,
                -0.07879367216781083,
                0.19639625633606106,
                0.039863039408116016,
                0.39080598019637536,
                -0.024199879462480412,
                0.2888665547884973,
                0.11339508461175582,
                0.5022145328068507,
                -0.15794447801641975,
                0.04347256913986598,
                -0.07617420588959413,
                0.20099584831430692,
                -0.12179390475059251,
                0.11749964561891449,
                -0.021085381307898287,
                0.29396117743094785,
                0.036279499631088785,
                0.3852423240345596,
                0.19182265746176164,
                0.6165385012678397,
                0.10931651506115425,
                0.4961558486863392,
                0.2837979270429394,
                0.7463902820684667,
                -0.18404901890126885,
                -0.01951840841464886,
                -0.12072196467331572,
                0.11956165094807525,
                -0.15712005448645022,
                0.04528705829921929,
                -0.07485474935746374,
                0.20330536971569824,
                -0.025747388255163938,
                0.2863289860889303,
                0.11135254545214257,
                0.49918193540455336,
                0.03806801532923608,
                0.38802089704014986,
                0.19410620230245823,
                0.6198121014504211,
                -0.12285936519520316,
                0.11544412110644964,
                -0.022645874049244636,
                0.2914106216832285,
                -0.07748718254763434,
                0.19869280811659157,
                0.041664560446617885,
                0.3935975620323917,
                0.10728700698856983,
                0.4931362862517237,
                0.28127339122517203,
                0.7428756941555843,
                0.1895456353761847,
                0.6132714259511282,
                0.38247027476668605,
                0.8819490911756263,
                -0.20405077442057495,
                -0.08562820717493011,
                -0.16377774143352036,
                0.030397829217286152,
                -0.1886488205445116,
                -0.03234975181180856,
                -0.12943753700960609,
                0.10261453606972651,
                -0.09065202536182593,
                0.17531629227312967,
                0.023393880958452174,
                0.36511521012030734,
                -0.03836363524225821,
                0.26548118777162144,
                0.09462052340280125,
                0.4742183595610593,
                -0.16531254158656525,
                0.026882896192908342,
                -0.08815307402813152,
                0.17979537027665,
                -0.13146737057757096,
                0.09860457016453256,
                -0.03536965181800163,
                0.2704552967288829,
                0.01993084523064785,
                0.3596720566919476,
                0.17086319682783938,
                0.5863574266990755,
                0.09066245760073308,
                0.4682801777979745,
                0.260533063116714,
                0.7139038036793786,
                -0.18917194049714325,
                -0.03386293885921514,
                -0.13045569060291934,
                0.10060631576506263,
                -0.16454837822917578,
                0.02863712551600601,
                -0.08689387751925404,
                0.18204463206645255,
                -0.03985089030341345,
                0.26300387220778043,
                0.09263823769565008,
                0.4712460149400819,
                0.021659110476276135,
                0.36239037992731316,
                0.17308649153832942,
                0.5895707775090868,
                -0.13247257243062274,
                0.09660930382080948,
                -0.03686988616036278,
                0.26796499888199204,
                -0.08940579218619099,
                0.17755258811842833,
                0.025135145788232432,
                0.3678465363322506,
                0.08869319613566262,
                0.46532086120208527,
                0.25806877354090163,
                0.710449461164323,
                0.16864642117170572,
                0.5831505970053507,
                0.35696025346912286,
                0.8472174539842549,
                -0.19773392784772575,
                -0.060868143588275234,
                -0.14823928648355594,
                0.0643795017847074,
                -0.17772116981027034,
                -0.0029788837830613457,
                -0.10928827777902464,
                0.14120701328296634,
                -0.06637403205523126,
                0.21803750754493179,
                0.056893484882682546,
                0.41705803755411974,
                -0.009474836712806458,
                0.3128132090173429,
                0.1327309329042941,
                0.530771993407697,
                -0.15001512871201533,
                0.06062352797581391,
                -0.06363405194678155,
                0.22275761234036817,
                -0.1115591531561842,
                0.1369560070101561,
                -0.0062398249529995314,
                0.3180283441766353,
                0.05318944273671743,
                0.4113738803823789,
                0.2133434069435317,
                0.6472808650138663,
                0.12853186129625588,
                0.5245928086641017,
                0.30762407989385476,
                0.7794380497263605,
                -0.17836481193741885,
                -0.004612592483697676,
                -0.11042695332388125,
                0.13907827169872558,
                -0.14913044535165892,
                0.062498276607606595,
                -0.06225433574440303,
                0.2251273929787201,
                -0.011082598470328041,
                0.31021538797036297,
                0.13062814106972065,
                0.5276791440232045,
                0.055038207979194564,
                0.4142127022283809,
                0.21568720099543398,
                0.6506147136283964,
                -0.11268487170866145,
                0.13484022483426483,
                -0.007860575598827321,
                0.315417531044215,
                -0.06500728661570451,
                0.22039431461387998,
                0.05875526149390317,
                0.41990987435658167,
                0.12644210766584557,
                0.5215130014620704,
                0.3050392988946323,
                0.7758632174977732,
                0.21100613948360544,
                0.6439535451508861,
                0.4085415861353615,
                0.9172420188185474
            ],
            "result_with_budget": [
                {
                    "portfolio": {
                        "AMGN": 3,
                        "CSCO": 10,
                        "TRV": 1
                    },
                    "budget": 1599.655616760254,
                    "difference": -1.6556167602539062,
                    "objective_value": -725.9862283043584
                }
            ],
            "result_with_budget_excited": [
                {
                    "portfolio": {
                        "AMGN": 0,
                        "CSCO": 15,
                        "TRV": 3
                    },
                    "budget": 1595.8658638000488,
                    "difference": 2.134136199951172,
                    "objective_value": -3186.1923911738127
                }
            ]
        },
        "qaoa_solution": {
            "two_most_probable_states": [
                "00100000010",
                "00100010000"
            ],
            "final_expectation_value": -0.20069461242777273,
            "params": [
                5.098202738693319,
                -4.137669646288884,
                4.846077664243983,
                2.9238064290162553,
                3.7127245641247626,
                -2.6416693691484414,
                5.8682585285869635,
                1.7660360607849988,
                4.425914361331593,
                -1.0689542134848502,
                3.9764974794550922,
                0.4794478683244995,
                2.3846756113093748,
                0.6087095598410481,
                1.7202436398066154,
                1.918382230969209,
                2.4054474194233917,
                2.519028709448502,
                2.0911240506440576,
                0.7562789342568218
            ],
            "total_steps": 800,
            "states_probs": [
                0.004051602236952147,
                0.004061456308480453
            ],
            "optimized_portfolios": [
                {
                    "AMGN": 4,
                    "CSCO": 0,
                    "TRV": 2
                },
                {
                    "AMGN": 4,
                    "CSCO": 8,
                    "TRV": 0
                }
            ],
            "training_history": {
                "xbest": [
                    5.098202738693319,
                    -4.137669646288884,
                    4.846077664243983,
                    2.9238064290162553,
                    3.7127245641247626,
                    -2.6416693691484414,
                    5.8682585285869635,
                    1.7660360607849988,
                    4.425914361331593,
                    -1.0689542134848502,
                    3.9764974794550922,
                    0.4794478683244995,
                    2.3846756113093748,
                    0.6087095598410481,
                    1.7202436398066154,
                    1.918382230969209,
                    2.4054474194233917,
                    2.519028709448502,
                    2.0911240506440576,
                    0.7562789342568218
                ],
                "fbest": -0.20069461242777273,
                "evals_best": 9563,
                "evaluations": 9600,
                "iterations": 800,
                "xfavorite": [
                    5.122782339904658,
                    -4.154035924429275,
                    4.85089553530308,
                    2.9350466696501374,
                    3.7201305828590394,
                    -2.648802489252355,
                    5.887976690475797,
                    1.7592371463353338,
                    4.432112061433521,
                    -1.0759257182933828,
                    3.9796591345571435,
                    0.4789128227099328,
                    2.3879446022924764,
                    0.6070023172257188,
                    1.719549154528486,
                    1.9170127994616104,
                    2.4029313378293646,
                    2.5224727068951505,
                    2.0883759807093907,
                    0.7588099465959282
                ],
                "stds": [
                    0.01493034143454515,
                    0.02052199606281565,
                    0.026733698926077663,
                    0.016277311308008104,
                    0.014590843461924088,
                    0.014563139523725522,
                    0.01593541790499865,
                    0.0129300477273397,
                    0.02395704751945912,
                    0.010114968874979483,
                    0.0030933313749470265,
                    0.004409452459623909,
                    0.0028429035367431004,
                    0.0041357067586090335,
                    0.0029402676508102333,
                    0.003306313619021465,
                    0.006149068937017366,
                    0.006669654939114512,
                    0.0067443449811137165,
                    0.00691082644790481
                ],
                "stop": {
                    "maxiter": 800
                }
            },
            "objective_values": [
                -15.326673497878602,
                -335.03917107855364
            ],
            "result_with_budget": [
                {
                    "portfolio": {
                        "AMGN": 4,
                        "CSCO": 0,
                        "TRV": 2
                    },
                    "budget": 1514.0216979980469,
                    "difference": 83.97830200195312
                },
                {
                    "portfolio": {
                        "AMGN": 4,
                        "CSCO": 8,
                        "TRV": 0
                    },
                    "budget": 1501.4795837402344,
                    "difference": 96.52041625976562
                }
            ]
        }
    }
}