{
    "99": {
        "hyperparams": {
            "stocks": [
                "AAPL",
                "AMGN",
                "AXP"
            ],
            "start": "2015-01-01",
            "end": "2025-01-01",
            "risk_aversion": 0.1,
            "n_qubits": 6,
            "budget": 848,
            "log_encoding": true,
            "layers": 6,
            "prices_now": {
                "AAPL": 250.1449737548828,
                "AMGN": 258.5511779785156,
                "AXP": 295.1141357421875
            },
            "assets_to_qubits": {
                "AAPL": [
                    0,
                    1
                ],
                "AMGN": [
                    2,
                    3
                ],
                "AXP": [
                    4,
                    5
                ]
            },
            "optimizer": "CMAES",
            "lambda_budget": 100
        },
        "continuous_variables_solution": {
            "weights": {
                "AAPL": 1.0,
                "AMGN": 1.6132928326584306e-16,
                "AXP": 0.0
            },
            "allocation": {
                "AAPL": 3,
                "AMGN": 0,
                "AXP": 0
            },
            "value": -1.0386239780108797,
            "left_overs": 97.56507826076665
        },
        "continuous_variables_solution_unconstrained": {
            "weights": {
                "AAPL": 1.0,
                "AMGN": 0.0,
                "AXP": 0.04287370922685425
            },
            "allocation": {
                "AAPL": 3,
                "AMGN": 0,
                "AXP": 0
            },
            "value": -1.0386239780108797,
            "left_overs": 97.56507861368584
        },
        "exact_solution": {
            "smallest_eigenvalues": [
                -0.30390443858036903
            ],
            "smallest_bitstrings": [
                "001001"
            ],
            "first_excited_energy": -0.30388011337360754,
            "optimized_portfolio": [
                {
                    "AAPL": 0,
                    "AMGN": 1,
                    "AXP": 2
                }
            ],
            "second_optimized_portfolio": [
                {
                    "AAPL": 1,
                    "AMGN": 0,
                    "AXP": 2
                }
            ],
            "spectrum": [
                2.36963794971313e-16,
                -0.27582345581109846,
                -0.1747183302524354,
                -0.3033153757389492,
                -0.25763111967758184,
                -0.27548278102737894,
                -0.30336355293504325,
                -0.17398880254041002,
                -0.15706687991601806,
                -0.30390443858036903,
                -0.2672922616836517,
                -0.26690340943055973,
                -0.3016927190213269,
                -0.19055848282376406,
                -0.2829322037107453,
                -0.024571554707634342,
                -0.2528094850876877,
                -0.2790485123802125,
                -0.30273560141661265,
                -0.1817482165592603,
                -0.29177826401853435,
                -0.06004549548273771,
                -0.21271848288561382,
                0.16624070008646055,
                -0.30054519466087265,
                -0.19779832418900914,
                -0.28597836230449475,
                -0.0360050786566189,
                -0.22650869280274985,
                0.13420997416152633,
                -0.08295596276954609,
                0.4249891201254033,
                -0.1528488715273322,
                -0.30388011337360754,
                -0.2651710949208374,
                -0.2689759257075087,
                -0.30114882093786105,
                -0.19420826773730002,
                -0.28448514715194373,
                -0.030318181038656113,
                -0.2552501663124303,
                -0.2772955107521255,
                -0.30307944114537727,
                -0.17789837371597186,
                -0.29054483509297957,
                -0.05461838395348668,
                -0.20938821259739318,
                0.1737646527325831,
                -0.29988184034356624,
                -0.20132865229281074,
                -0.2874118493019596,
                -0.04163224765579918,
                -0.22951944847932113,
                0.12700553637719217,
                -0.08806355959547021,
                0.4156878415761261,
                -0.29295196457245354,
                -0.06541287830152656,
                -0.2159890246718121,
                0.15877647643729378,
                -0.10958429165896595,
                0.3759265922135498,
                0.09636454636477006,
                0.7291018482634034
            ],
            "result_with_budget": [
                {
                    "portfolio": {
                        "AAPL": 0,
                        "AMGN": 1,
                        "AXP": 2
                    },
                    "budget": 848.7794494628906,
                    "difference": -0.779449462890625,
                    "objective_value": -1.9924793601701372
                }
            ],
            "result_with_budget_excited": [
                {
                    "portfolio": {
                        "AAPL": 1,
                        "AMGN": 0,
                        "AXP": 2
                    },
                    "budget": 840.3732452392578,
                    "difference": 7.6267547607421875,
                    "objective_value": -2.0561216764033587
                }
            ]
        },
        "qaoa_solution": {
            "two_most_probable_states": [
                "100001",
                "101010"
            ],
            "final_expectation_value": -0.2902326205421664,
            "params": [
                1.2810567449663859,
                2.936700021740887,
                4.416785351401493,
                0.918494933734686,
                8.426288534151007,
                12.466862926817463,
                2.6649452433665513,
                2.899799420171976,
                1.5476342747648217,
                1.4294140254384784,
                3.040573257289897,
                -0.0592685220631617
            ],
            "total_steps": 536,
            "states_probs": [
                0.055668584393356736,
                0.06077252058741564
            ],
            "optimized_portfolios": [
                {
                    "AAPL": 1,
                    "AMGN": 0,
                    "AXP": 2
                },
                {
                    "AAPL": 1,
                    "AMGN": 1,
                    "AXP": 1
                }
            ],
            "training_history": {
                "xbest": [
                    1.2810567449663859,
                    2.936700021740887,
                    4.416785351401493,
                    0.918494933734686,
                    8.426288534151007,
                    12.466862926817463,
                    2.6649452433665513,
                    2.899799420171976,
                    1.5476342747648217,
                    1.4294140254384784,
                    3.040573257289897,
                    -0.0592685220631617
                ],
                "fbest": -0.2902326205421664,
                "evals_best": 5882,
                "evaluations": 5896,
                "iterations": 536,
                "xfavorite": [
                    1.2810558233202876,
                    2.936699271225357,
                    4.416786233032431,
                    0.9184954897257,
                    8.426289741482268,
                    12.466867323811236,
                    2.6649452235810593,
                    2.899799364941939,
                    1.5476337401207685,
                    1.429414503149862,
                    3.0405731203953263,
                    -0.05926854478178542
                ],
                "stds": [
                    3.4237021543019168e-06,
                    6.072705276091792e-06,
                    7.000114173159779e-06,
                    3.6367097791199283e-06,
                    1.1473939521908399e-05,
                    1.0778067888933864e-05,
                    6.903635911886834e-07,
                    5.986212037926108e-07,
                    7.232296004202795e-07,
                    6.578197071907282e-07,
                    1.2850647073355553e-07,
                    8.865139961981479e-08
                ],
                "stop": {
                    "tolfun": 1e-11
                }
            },
            "objective_values": [
                -2.0561216764033587,
                -0.32187409596582456
            ],
            "result_with_budget": [
                {
                    "portfolio": {
                        "AAPL": 1,
                        "AMGN": 0,
                        "AXP": 2
                    },
                    "budget": 840.3732452392578,
                    "difference": 7.6267547607421875
                },
                {
                    "portfolio": {
                        "AAPL": 1,
                        "AMGN": 1,
                        "AXP": 1
                    },
                    "budget": 803.8102874755859,
                    "difference": 44.18971252441406
                }
            ]
        }
    }
}