{
    "5": {
        "hyperparams": {
            "stocks": [
                "AXP",
                "TRV"
            ],
            "start": "2015-01-01",
            "end": "2025-01-01",
            "risk_aversion": 0.1,
            "n_qubits": 10,
            "budget": 5354,
            "log_encoding": true,
            "layers": 10,
            "prices_now": {
                "AXP": 295.1141052246094,
                "TRV": 239.9084930419922
            },
            "assets_to_qubits": {
                "AXP": [
                    0,
                    1,
                    2,
                    3,
                    4
                ],
                "TRV": [
                    5,
                    6,
                    7,
                    8,
                    9
                ]
            },
            "optimizer": "CMAES",
            "lambda_budget": 0.01
        },
        "continuous_variables_solution": {
            "weights": {
                "AXP": 0.7191371317131737,
                "TRV": 0.28086286828682633
            },
            "allocation": {
                "AXP": 13,
                "TRV": 6
            },
            "value": -6513.473867071779,
            "left_overs": 78.06565350015626
        },
        "continuous_variables_solution_unconstrained": {
            "weights": {
                "AXP": 0.7065864379222404,
                "TRV": 0.26318513541951455
            },
            "allocation": {
                "AXP": 13,
                "TRV": 6
            },
            "value": -6513.473867071779,
            "left_overs": 78.06567472091774
        },
        "exact_solution": {
            "smallest_eigenvalues": [
                -0.24279091120506177
            ],
            "smallest_bitstrings": [
                "0111010100"
            ],
            "first_excited_energy": -0.24276986555157906,
            "optimized_portfolio": [
                {
                    "AXP": 14,
                    "TRV": 5
                }
            ],
            "second_optimized_portfolio": [
                {
                    "AXP": 13,
                    "TRV": 6
                }
            ],
            "spectrum": [
                6.422373212671556e-17,
                -0.2232347191501544,
                -0.14316547623882905,
                -0.2388905378576405,
                -0.07942021318217372,
                -0.23922940128574063,
                -0.19114978909424538,
                -0.22192239869994404,
                -0.04166614849745609,
                -0.23325731842345096,
                -0.16913517459183677,
                -0.23250565902577322,
                -0.11325635959367668,
                -0.24111891701527363,
                -0.20919037715494213,
                -0.20709559802776598,
                -0.02132184808062874,
                -0.22875045817715736,
                -0.15664365499380142,
                -0.23622020170926608,
                -0.09682851883494502,
                -0.2406866112212994,
                -0.20066814835084065,
                -0.215042391344511,
                -0.06103247916473398,
                -0.23675160077062798,
                -0.18063797443085747,
                -0.227741572172425,
                -0.12870249411445592,
                -0.2405218002910917,
                -0.21671359564630785,
                -0.19807586185680745,
                -0.23953080110027883,
                -0.15180738583771122,
                -0.22792323472756523,
                -0.00909231003863634,
                -0.24169263953065193,
                -0.08893820565292375,
                -0.1980398674258306,
                0.08812275036052908,
                -0.2425937539109854,
                -0.12247240523470589,
                -0.2150092644885153,
                0.0373174983327135,
                -0.23680953360011794,
                -0.051160646471931547,
                -0.17698401104971448,
                0.14338069479588111,
                -0.24155679364115315,
                -0.1376621671288667,
                -0.2219713664394705,
                0.013566613727833958,
                -0.23975008379069582,
                -0.07058273281019428,
                -0.1880248141916521,
                0.11519142997123293,
                -0.24263974858669343,
                -0.10623288979948615,
                -0.20703335703528672,
                0.06216719264807408,
                -0.2328682363776711,
                -0.03066591702422836,
                -0.16491306690244062,
                0.17269821296471036,
                -0.1672879745676504,
                -0.2356544765416456,
                -0.23330160189115814,
                -0.17264253088490547,
                -0.2081786484129857,
                -0.21245838080540916,
                -0.24252247533171198,
                -0.11586283701948967,
                -0.18969792720222226,
                -0.22611444048193244,
                -0.23991024424095306,
                -0.1463967182007637,
                -0.22271825879012377,
                -0.19464820184098372,
                -0.24111330762298114,
                -0.08098968353935444,
                -0.17898349035888692,
                -0.2313967084935352,
                -0.23710404076124478,
                -0.16005256087645628,
                -0.21594196292795972,
                -0.2040750652227157,
                -0.24232225605764965,
                -0.09897199756347598,
                -0.19943010739324088,
                -0.21980321776976228,
                -0.24171739610953755,
                -0.13166890960442343,
                -0.228505539036897,
                -0.18417251666497378,
                -0.23889199454879698,
                -0.06190898243555591,
                -0.2156284928194893,
                0.0300441015858454,
                -0.1256116070467545,
                0.253816454228263,
                -0.17870280929532492,
                0.13322806325736283,
                -0.05612380721385446,
                0.39225008344866,
                -0.19917394661462487,
                0.07948603117315133,
                -0.09293377240250268,
                0.3207730153524804,
                -0.15419111155308848,
                0.19132038340825533,
                -0.015144634041670883,
                0.4683109522172129,
                -0.20790192353366835,
                0.05423056215640787,
                -0.1097870167118203,
                0.28673349926606395,
                -0.1669536565679435,
                0.1617271727172748,
                -0.03615781697473896,
                0.4297034588835252,
                -0.18944187312060787,
                0.10581647461048584,
                -0.07504754666072144,
                0.3559426069782521,
                -0.14041166605084468,
                0.22201448056287945,
                0.006920888301595076,
                0.508080987198626,
                -0.09548575083068507,
                -0.24139922628494806,
                -0.20011404690178444,
                -0.21783065972490315,
                -0.15565614445036421,
                -0.23784884590287306,
                -0.22874927831185712,
                -0.18102475778775998,
                -0.1275301709399013,
                -0.24166456559110497,
                -0.21641843087446952,
                -0.20154821574434514,
                -0.17985481442692766,
                -0.22991699402383278,
                -0.23708462414816459,
                -0.15621210452809062,
                -0.11199734116077885,
                -0.2420399642466368,
                -0.20876168614751586,
                -0.21021668115777456,
                -0.16824707394791846,
                -0.23439975657106868,
                -0.23341788975584607,
                -0.16915771991284037,
                -0.14208344027297085,
                -0.24026895339061108,
                -0.22308184267123407,
                -0.19181954804054416,
                -0.19047774673414566,
                -0.22439566207525993,
                -0.23974622381923774,
                -0.14218137693127583,
                -0.23969640720134308,
                -0.07327065772103002,
                -0.189002620649275,
                0.10978386435440905,
                -0.22236928237573492,
                0.009665739173509474,
                -0.13938952295940785,
                0.2275003469744141,
                -0.23302690385514754,
                -0.03392618413292061,
                -0.16624185563658903,
                0.16641422351706506,
                -0.20770259592927418,
                0.05755227529336483,
                -0.10841156765326372,
                0.2931025059521986,
                -0.2368589891268714,
                -0.05412653245740972,
                -0.17813168367480317,
                0.13754571234142085,
                -0.21553850945958805,
                0.03306910492922685,
                -0.12441850457932367,
                0.25973302706255474,
                -0.22819784025375486,
                -0.012664024582486746,
                -0.1533291868858866,
                0.19639662456274717,
                -0.19885841139421082,
                0.08312165768916481,
                -0.0913639432743167,
                0.3276168295829154,
                -0.21534085898231312,
                -0.2058549624609399,
                -0.242622481363004,
                -0.10314079626297705,
                -0.23690198903377305,
                -0.16289257472635935,
                -0.23234379650218215,
                -0.026231357512780922,
                -0.22809364315199496,
                -0.18645147373278606,
                -0.23949499294350055,
                -0.06685584941651825,
                -0.24175099474315867,
                -0.13513714729589676,
                -0.22114088202392382,
                0.01878690572463493,
                -0.2222095024944498,
                -0.19667020250662523,
                -0.24156007803912186,
                -0.08553750483872079,
                -0.23982246878688399,
                -0.14954212495733113,
                -0.22725068265270446,
                -0.004274964462146005,
                -0.2329917254411998,
                -0.17519394359301418,
                -0.23642403204606063,
                -0.047089358933631545,
                -0.24268519213068382,
                -0.11967198993748378,
                -0.21401038132759734,
                0.04296154336846481,
                -0.16707008274289084,
                0.15847356252546665,
                -0.03745337109281379,
                0.42338197764084123,
                -0.11041632126991426,
                0.2821053608488694,
                0.052074026445700805,
                0.5827684016488616,
                -0.14076794507374937,
                0.21811087302990265,
                0.005221769944774175,
                0.5007803538007158,
                -0.0759882195482129,
                0.35051023402681425,
                0.10314349832377569,
                0.6694124373603607,
                -0.15442364069779665,
                0.18775076810705812,
                -0.016635561771412347,
                0.46151147351159855,
                -0.0937136451443334,
                0.3157530457561033,
                0.07707897620889335,
                0.6255041482516609,
                -0.12609992911966375,
                0.24956022107774492,
                0.028123329323160032,
                0.5411966008082645,
                -0.05723615847230325,
                0.38638408870291,
                0.1302731173159267,
                0.7145020705331995,
                -0.0507010698637794,
                -0.23529840243711478,
                -0.17460515161526627,
                -0.23136691226352055,
                -0.12049886555320717,
                -0.24153188968045294,
                -0.21292183807555295,
                -0.20449565012172424,
                -0.08755732393392622,
                -0.24044776353269234,
                -0.19574537356444352,
                -0.22004085368267942,
                -0.14951834902381114,
                -0.23851721892131042,
                -0.226114091320146,
                -0.18468463149093214,
                -0.06961820485818583,
                -0.23837926774002602,
                -0.18566958191442354,
                -0.22622848722409503,
                -0.13549945167229513,
                -0.24053912954577553,
                -0.22001739747953017,
                -0.19512641257975363,
                -0.10451781610058507,
                -0.24150000179203937,
                -0.20483027705858162,
                -0.21279848509987068,
                -0.162554127359175,
                -0.23546145052581866,
                -0.23120885083249085,
                -0.17316396105769125,
                -0.24262860008644468,
                -0.11561710060149359,
                -0.21150504302825782,
                0.04722289077539674,
                -0.23505841108116884,
                -0.042735610332253246,
                -0.1717736867638394,
                0.15466294197551822,
                -0.2408312755374308,
                -0.08128774626370763,
                -0.19367583714064127,
                0.09873039076510771,
                -0.2252905711211621,
                8.495905063884411e-05,
                -0.1457660481707206,
                0.2150793043950344,
                -0.24222579358465132,
                -0.09897754589978687,
                -0.20309765217174006,
                0.07242705385785181,
                -0.23067520577300268,
                -0.021861861072435654,
                -0.1592852154863534,
                0.1843068462757744,
                -0.23844292371703382,
                -0.06254230243284663,
                -0.1832358371908813,
                0.12613993927390288,
                -0.2189015656397327,
                0.023111068555544536,
                -0.13121160481469576,
                0.24698817336820142,
                -0.19428906428056444,
                -0.2237725260856833,
                -0.24095384663302669,
                -0.1409443158148577,
                -0.2255224394693837,
                -0.19070960166877762,
                -0.2404368362023552,
                -0.07412048886459531,
                -0.21187389292546185,
                -0.20930864597356122,
                -0.2427000948604632,
                -0.10968902935088932,
                -0.23522131326517617,
                -0.16793578626290526,
                -0.23413757188091153,
                -0.03418597931691161,
                -0.2035728049592764,
                -0.21705513413101649,
                -0.2423266309429147,
                -0.12585266265481104,
                -0.23086655038533146,
                -0.17984714379434255,
                -0.2377934889322507,
                -0.0547024029224569,
                -0.219190961570039,
                -0.20052841797157586,
                -0.24207123326026128,
                -0.09244713374502146,
                -0.23858454224167094,
                -0.15497006617455952,
                -0.229465260664762,
                -0.01256411663172342,
                -0.1944285275197807,
                0.09109658562289526,
                -0.08464881011641921,
                0.33538220003758396,
                -0.14765624016547238,
                0.20447818639801182,
                -0.005163068614014658,
                0.4842615253904082,
                -0.1730586267774686,
                0.14562334243503414,
                -0.046982974489710734,
                0.4075445944263775,
                -0.1181958871379546,
                0.2677128143189381,
                0.04084949618714295,
                0.5655977978674224,
                -0.18424617335730856,
                0.11782205617646617,
                -0.0663328673009971,
                0.37089800245959725,
                -0.13343502999685672,
                0.2355446683041986,
                0.017316591619513644,
                0.5243480656220948,
                -0.16086300993384292,
                0.17450659927767673,
                -0.026594615319812828,
                0.44532976933333196,
                -0.10193511448418328,
                0.3009895985794723,
                0.06544098070978573,
                0.6080193347799622,
                -0.13435029675456436,
                -0.24152348264366066,
                -0.21968343500031065,
                -0.19826309123987354,
                -0.18488581325153322,
                -0.22816407142704778,
                -0.23862089222912605,
                -0.15148854222017769,
                -0.16157969813124914,
                -0.23689277131071398,
                -0.23114437418586173,
                -0.1770078109708755,
                -0.2042582739429348,
                -0.21530079855890663,
                -0.24208951282698568,
                -0.12165559242338718,
                -0.1484548882232645,
                -0.23971821702800525,
                -0.2259106179760151,
                -0.18816547188940055,
                -0.1950645264207124,
                -0.2222516711522344,
                -0.2408577849867646,
                -0.13711451124690685,
                -0.17372373767876823,
                -0.23304287965937728,
                -0.2353820763137717,
                -0.1647842041355604,
                -0.21246524776028572,
                -0.20730636855649073,
                -0.24231262917554555,
                -0.10510506214271655,
                -0.2307065809259153,
                -0.024730453773421177,
                -0.16038334511963806,
                0.17863319507322048,
                -0.2035951214193312,
                0.0683059367632239,
                -0.10085226306559696,
                0.3066800402079971,
                -0.21915175210709595,
                0.01965112981853488,
                -0.13267345226740057,
                0.24041282620138524,
                -0.18401423079145343,
                0.12128264139308602,
                -0.06488421131242463,
                0.3774966195561337,
                -0.2254281161297643,
                -0.003070900759845613,
                -0.14704021585869076,
                0.20896579617235064,
                -0.19430924023644228,
                0.09425088171264263,
                -0.08338894590463294,
                0.3415156698013441,
                -0.21187498882082653,
                0.043441415031463176,
                -0.11727891579235407,
                0.27298170074639483,
                -0.17270677378911528,
                0.14940781213246254,
                -0.045333101477393854,
                0.41463112431660265,
                -0.230427664840291,
                -0.18187612993096916,
                -0.238286831296563,
                -0.05920133554089664,
                -0.24229911279758895,
                -0.128979153765748,
                -0.21822019097070697,
                0.027837684200280485,
                -0.23834023881123614,
                -0.15751602278518115,
                -0.23027301846755752,
                -0.017865296471304266,
                -0.24228787367752583,
                -0.09622289348957237,
                -0.2020988275535512,
                0.07796334398759229,
                -0.23487726651281174,
                -0.17021563526492525,
                -0.23478308464635037,
                -0.039075828120829256,
                -0.24279091120506177,
                -0.11313123988028494,
                -0.21067004933953457,
                0.052344067600773855,
                -0.240814837317148,
                -0.14377227104066093,
                -0.22475324982543896,
                0.004436919375083578,
                -0.24078743653840054,
                -0.07824827388437007,
                -0.19250232341984677,
                0.10470299258630587,
                -0.13351356928330846,
                0.23222458340291277,
                0.016019280181493737,
                0.5178703190993091,
                -0.06694097292717933,
                0.36616162819524917,
                0.11563453859868415,
                0.6878277347612519,
                -0.1022610670599755,
                0.29699941930508883,
                0.06372627629636397,
                0.6005360707747474,
                -0.027524783864411987,
                0.43976592935517506,
                0.17178567823959914,
                0.7798131384712413,
                -0.11839411373063131,
                0.2640668716765255,
                0.03935009265335586,
                0.5586290671023323,
                -0.04774679970991201,
                0.40240496927729136,
                0.14317702004578245,
                0.7332293519284474,
                -0.08511117361558905,
                0.33102875897701245,
                0.08915272528259911,
                0.6435995013212927,
                -0.006270850476762697,
                0.47825186037547457,
                0.20146622661038036,
                0.8275880848525416,
                -0.026089966086489582,
                -0.23001117814702618,
                -0.1596262326712833,
                -0.2358792520426485,
                -0.1006994379396683,
                -0.24112794127338674,
                -0.20277830525627297,
                -0.21396333533956066,
                -0.06535133198461983,
                -0.23759842845555237,
                -0.18318191019158483,
                -0.2270256062152636,
                -0.13212769387249032,
                -0.24056691026011104,
                -0.21839571965556662,
                -0.19664652494448467,
                -0.04620952265758162,
                -0.2343100981004381,
                -0.17189787860936237,
                -0.2319757656146432,
                -0.11690408704789228,
                -0.2413609221510021,
                -0.21108574418629358,
                -0.20583974524547324,
                -0.08351487752952257,
                -0.23987237564162914,
                -0.19347617236353856,
                -0.22102334175743985,
                -0.14636892261721632,
                -0.2387412927718088,
                -0.2247052573515164,
                -0.18637742309135955,
                -0.24183183865895472,
                -0.13447952938782745,
                -0.22047274548506032,
                0.018287113619558492,
                -0.23913062126484122,
                -0.06660936307367188,
                -0.18566944710508218,
                0.1206083949965835,
                -0.24246606264211,
                -0.10264987727950108,
                -0.20510312002891593,
                0.06724269968313956,
                -0.2318068345493198,
                -0.026313090531238845,
                -0.16213993860509338,
                0.17844220392962815,
                -0.24264411933105964,
                -0.1190883830899968,
                -0.21329407994275837,
                0.0422171402591365,
                -0.2359685665820647,
                -0.0469961306185628,
                -0.17441878706797434,
                0.148963031978459,
                -0.2412956408166899,
                -0.08515870714826526,
                -0.19589619945178607,
                0.09337073521597296,
                -0.2266425781330262,
                -0.004554118745459052,
                -0.14882841616652864,
                0.20905367343266182,
                -0.18153131711259066,
                -0.23046646615285962,
                -0.23787450001617164,
                -0.15755478829371325,
                -0.2175950542850257,
                -0.20234087975116702,
                -0.24222924968623075,
                -0.0957580570705125,
                -0.2015294949856443,
                -0.21846640081002108,
                -0.24205328529298645,
                -0.12880668421761735,
                -0.2297153599822501,
                -0.18205105168653732,
                -0.23837665003678252,
                -0.058356947432002385,
                -0.19202132169063416,
                -0.2249798152494206,
                -0.24046276432666805,
                -0.14371518218485477,
                -0.224149281532276,
                -0.1927190603092723,
                -0.24080825732337655,
                -0.07760493803554609,
                -0.21005456484087134,
                -0.2109216736452528,
                -0.24264315224204705,
                -0.11282310668626282,
                -0.23429119822003333,
                -0.17033148543538887,
                -0.23493069789520502,
                -0.038007078295978644,
                -0.20579596245556378,
                0.059782762263889025,
                -0.10590661988503162,
                0.2937983647358847,
                -0.1639511801476453,
                0.16805912933636766,
                -0.03142515785845749,
                0.4374473223618968,
                -0.18688577145327448,
                0.1117639674825522,
                -0.07073736997573066,
                0.36335415175645147,
                -0.1369674636115071,
                0.22871918901377794,
                0.012067849524593905,
                0.5161419258713015,
                -0.1968424996934768,
                0.08523717610901614,
                -0.08883762864935303,
                0.3280129603714127,
                -0.15096713585042645,
                0.19784023511375756,
                -0.010203746150355263,
                0.47621531391207306,
                -0.17592299434087263,
                0.13936919681124152,
                -0.05160142195375056,
                0.3998296378340748,
                -0.12194856077863923,
                0.2607028707213377,
                0.0353948703349687,
                0.5572356764408177,
                -0.11565839148376304,
                -0.2422093988301943,
                -0.2106418414698016,
                -0.20880207471493487,
                -0.1710124365784548,
                -0.23375780408673838,
                -0.234430381335374,
                -0.16701625580216387,
                -0.14529577815053704,
                -0.24002829425038327,
                -0.22452553172762343,
                -0.19003534677862102,
                -0.19279875421370093,
                -0.22336209952417166,
                -0.2403336696086011,
                -0.13969586483983795,
                -0.13096670307148198,
                -0.24162790844641333,
                -0.21807974964628143,
                -0.19994732557677633,
                -0.1823976167888637,
                -0.2290779709153518,
                -0.23788376869066977,
                -0.15389690938743075,
                -0.15864472237351332,
                -0.23740638486203022,
                -0.22997665485008265,
                -0.17906032842406536,
                -0.2022141352473875,
                -0.21660519927495955,
                -0.24177673196725977,
                -0.1244064930048173,
                -0.23596054250898682,
                -0.049777242771175616,
                -0.17545974510935,
                0.14341970687128808,
                -0.21374483085521837,
                0.03820335941256858,
                -0.1208923412594841,
                0.2662944737070704,
                -0.22685009758828337,
                -0.007917040852706978,
                -0.15022669009357223,
                0.20262132259025403,
                -0.1966230398572931,
                0.08863187673842322,
                -0.08742188802394993,
                0.3345001870661468,
                -0.23190344438098756,
                -0.029376799694769615,
                -0.16335383167639236,
                0.172465258974727,
                -0.20568748530173267,
                0.06287598051422406,
                -0.10467643136243186,
                0.2998268179194621,
                -0.22079809654612428,
                0.014607716372422096,
                -0.13607427625980997,
                0.23389521885160822,
                -0.1865482696789845,
                0.11547754996073896,
                -0.06912384788479303,
                0.3703227215390277,
                -0.22363098305793697,
                -0.19462492496926134,
                -0.2412066007799941,
                -0.08194009001786016,
                -0.24034960733666397,
                -0.146699789313229,
                -0.22603737897076356,
                2.8487424197894354e-05,
                -0.23396476067106423,
                -0.1727453310848643,
                -0.23563760145343374,
                -0.043132353867289,
                -0.24276986555157906,
                -0.11644642588992417,
                -0.21237716769819046,
                0.047597415751667545,
                -0.22929063764808258,
                -0.18420338241177928,
                -0.23892433416820355,
                -0.06307705172583557,
                -0.24205641660349284,
                -0.1321018304274006,
                -0.21971669779441536,
                0.023258376330904943,
                -0.23765170216079937,
                -0.16024584398977543,
                -0.23134311415327138,
                -0.022099430927148753,
                -0.24248748495667596,
                -0.09972782944389337,
                -0.204014680941512,
                0.07305299045972212,
                -0.15106917560040614,
                0.1945491038463706,
                -0.011504599298462873,
                0.46981155295771804,
                -0.08946082243616142,
                0.3233264886344114,
                0.08306079741932133,
                0.634475330513112,
                -0.12229419943496304,
                0.25675172775912264,
                0.03368357274209213,
                0.5498396148299411,
                -0.05254129720216111,
                0.39432735013535264,
                0.13666793026570248,
                0.723785771800982,
                -0.13718738141832768,
                0.22510714340228574,
                0.010568280603921835,
                0.5092536911454814,
                -0.07151369057026434,
                0.35827015606864254,
                0.10933294384149984,
                0.6785418904602615,
                -0.10638646844689405,
                0.2894892951529581,
                0.05784607683579565,
                0.5915774007635015,
                -0.032539661870268674,
                0.4315053283287831,
                0.16507137566984134,
                0.7702158705458442,
                -0.07383312308750063,
                -0.23909495853807158,
                -0.18810142220741952,
                -0.2253514624189182,
                -0.13881799646892715,
                -0.24043950171509623,
                -0.22157926537923248,
                -0.19351697563560197,
                -0.1082837804462584,
                -0.2418037345177753,
                -0.20682459819230717,
                -0.21154918967193545,
                -0.165427669839027,
                -0.23496794255228146,
                -0.23234421432107902,
                -0.17120739460152787,
                -0.09154762861069875,
                -0.2409564557862002,
                -0.19795787621825198,
                -0.2189762326089099,
                -0.15261403532691623,
                -0.23821941078640382,
                -0.22746190823032345,
                -0.18289994810914514,
                -0.12404087315143066,
                -0.24163281225739017,
                -0.21469924417050676,
                -0.20306471261625916,
                -0.17725737530434613,
                -0.23068029527915748,
                -0.23622302043425628,
                -0.1584328748628485,
                -0.24191791021676826,
                -0.09521567907474848,
                -0.2010163295721866,
                0.07772006445182966,
                -0.22947252250415903,
                -0.017312215715211746,
                -0.1563484773076371,
                0.1902917456297795,
                -0.23768606177622006,
                -0.058381436128617376,
                -0.1807234623839721,
                0.13178577025631616,
                -0.21725710118542155,
                0.028038389641905245,
                -0.12785807499738205,
                0.25329750617929264,
                -0.2402985634085741,
                -0.07732515732690341,
                -0.19137820751406995,
                0.10420147537430442,
                -0.22386643706066092,
                0.0048248853690172865,
                -0.14261991252495015,
                0.22122830502299953,
                -0.23407818863962346,
                -0.03837902176714815,
                -0.1690482389854792,
                0.16048008132693606,
                -0.2096414789401936,
                0.05233461007435983,
                -0.11205829027035462,
                0.28650730058589674,
                -0.20555953436639687,
                -0.21556972939696165,
                -0.24253733741755926,
                -0.122807563886194,
                -0.23195881095138934,
                -0.17756130830559183,
                -0.2371426192464259,
                -0.05094627153009819,
                -0.22072928366175307,
                -0.19863809337465052,
                -0.2418482129644726,
                -0.08904004838368727,
                -0.23923396996948496,
                -0.15229901166269125,
                -0.2283933018669613,
                -0.008472762667695224,
                -0.21363618063226422,
                -0.20761966036779425,
                -0.2426932584584454,
                -0.10646137489680603,
                -0.2360916986450817,
                -0.16545599959790339,
                -0.23327525742323765,
                -0.03026045352519496,
                -0.226837382393447,
                -0.18862029032345493,
                -0.2399991013578949,
                -0.07053720773643322,
                -0.24138334460501806,
                -0.13808478714771494,
                -0.22249283374168652,
                0.014423996910970478,
                -0.18152151938535252,
                0.1239914855276316,
                -0.06183288649513937,
                0.3785744966171164,
                -0.12981300941252313,
                0.24249145961655796,
                0.022668063074746964,
                0.5326995403274443,
                -0.15768768830567245,
                0.181070225550112,
                -0.02166513904391781,
                0.4533510355007638,
                -0.09787124654140013,
                0.3083076401527466,
                0.07120606415599649,
                0.616685571653575,
                -0.17010819807100278,
                0.1519911940508993,
                -0.04226736359360096,
                0.41539523984174925,
                -0.11435228124357817,
                0.27484677529023516,
                0.04640887671751402,
                0.5741086396342134,
                -0.14425701779061004,
                0.21123482935668117,
                -2.1602031009236263e-05,
                0.49244977144190233,
                -0.08036611374907295,
                0.34288112279366834,
                0.09706505546344014,
                0.6604390434914306,
                -0.15156053166831737,
                -0.23933929751259506,
                -0.2272372698995502,
                -0.1862109064679778,
                -0.19727502818533246,
                -0.22106515640155341,
                -0.24131894208985807,
                -0.1344385029005655,
                -0.1763808402525168,
                -0.23225566090459657,
                -0.2362732450006745,
                -0.16246264983461964,
                -0.2142319716756134,
                -0.2057304439510417,
                -0.2423501292453137,
                -0.10208801748275427,
                -0.16446088381398125,
                -0.23630863195128812,
                -0.23225265571558143,
                -0.17486823943653287,
                -0.20624647873182475,
                -0.2139182879320959,
                -0.24233799191350178,
                -0.11880733352265903,
                -0.1873193177318411,
                -0.22717602408777884,
                -0.23929631598641735,
                -0.14898813886116777,
                -0.22122960450645127,
                -0.1964964449154846,
                -0.2413518130587173,
                -0.08427373672161544,
                -0.22393060055574468,
                0.0018748764065972976,
                -0.14376887616476444,
                0.2154301187135604,
                -0.19191592086219336,
                0.09997894966933522,
                -0.07926443255287724,
                0.34866314754004296,
                -0.209927789860454,
                0.048783650669916565,
                -0.11357744198795151,
                0.27979467975855876,
                -0.16987177987112753,
                0.15551020335596102,
                -0.04079352603907082,
                0.42209806013975626,
                -0.21742900464944445,
                0.024796409309100518,
                -0.12918621387894963,
                0.24705319151501967,
                -0.18139946323046388,
                0.12719936479571495,
                -0.06055111455368327,
                0.3848057615984239,
                -0.20142436169935649,
                0.07384247201112244,
                -0.09693832748602348,
                0.3136620934825839,
                -0.15732945703660237,
                0.18491815613031545,
                -0.019986614745128296,
                0.4605483724606118,
                -0.23572847589379806,
                -0.16760490367250538,
                -0.23386012185814317,
                -0.034920236539538296,
                -0.2427477656714763,
                -0.1097266831008643,
                -0.20888887013795096,
                0.05720084041750955,
                -0.24121749348218527,
                -0.14075971950543015,
                -0.22339803727655708,
                0.008949774718731048,
                -0.2403021237211793,
                -0.07446240945704205,
                -0.1903023435711966,
                0.10988945368919951,
                -0.23896688282568598,
                -0.15470320956513198,
                -0.22913320059162004,
                -0.01352945990378035,
                -0.24202313501914532,
                -0.09262629050555872,
                -0.20010729709662609,
                0.08298679477687719,
                -0.24247846899254552,
                -0.12576931758999083,
                -0.21665115452587405,
                0.032524221747734415,
                -0.23758207364866393,
                -0.055229104793740165,
                -0.17946971291641803,
                0.13791639083238036,
                -0.1143978484344066,
                0.27150666179026506,
                0.04512430532323658,
                0.56756555927977,
                -0.04285104607628208,
                0.41061775143604756,
                0.14980159926946454,
                0.7428332089169364,
                -0.08066297693684836,
                0.338860763917721,
                0.09535607423851768,
                0.6528771605040421,
                -0.0009327972135319785,
                0.48683309924569457,
                0.2085032471858899,
                0.8375022875495425,
                -0.09803834445014319,
                0.30463669135232374,
                0.06971599018044382,
                0.6096449624236827,
                -0.022407168069216703,
                0.44816453511408955,
                0.17861763193479088,
                0.7895742050072448,
                -0.06226839578643671,
                0.3741855066272001,
                0.12204954612187251,
                0.6972704191779222,
                0.021576235857022095,
                0.5266308902297714,
                0.23946425290534115,
                0.8866265414590689
            ],
            "result_with_budget": [
                {
                    "portfolio": {
                        "AXP": 14,
                        "TRV": 5
                    },
                    "budget": 5331.139938354492,
                    "difference": 22.860061645507812,
                    "objective_value": -6976.926785270012
                }
            ],
            "result_with_budget_excited": [
                {
                    "portfolio": {
                        "AXP": 13,
                        "TRV": 6
                    },
                    "budget": 5275.934326171875,
                    "difference": 78.065673828125,
                    "objective_value": -6513.473867071779
                }
            ]
        },
        "qaoa_solution": {
            "two_most_probable_states": [
                "0110011110",
                "1110010110"
            ],
            "final_expectation_value": -0.2303433200653009,
            "params": [
                2.3990443375605386,
                0.3222574530357157,
                3.140109874635383,
                2.535017944878994,
                6.076717539887998,
                -2.5260349377679487,
                2.1140256354791562,
                14.817759558761676,
                12.645574497740448,
                -0.1630158923856596,
                1.1582713114605532,
                1.1749811153935346,
                2.709323555221652,
                -0.16733204593563417,
                1.9534642337355357,
                2.9510763164683875,
                1.119373619601522,
                3.065887997897676,
                2.310742720291557,
                0.7703239556969739
            ],
            "total_steps": 800,
            "states_probs": [
                0.0056531611311412995,
                0.005705130464764756
            ],
            "optimized_portfolios": [
                {
                    "AXP": 6,
                    "TRV": 15
                },
                {
                    "AXP": 7,
                    "TRV": 13
                }
            ],
            "training_history": {
                "xbest": [
                    2.3990443375605386,
                    0.3222574530357157,
                    3.140109874635383,
                    2.535017944878994,
                    6.076717539887998,
                    -2.5260349377679487,
                    2.1140256354791562,
                    14.817759558761676,
                    12.645574497740448,
                    -0.1630158923856596,
                    1.1582713114605532,
                    1.1749811153935346,
                    2.709323555221652,
                    -0.16733204593563417,
                    1.9534642337355357,
                    2.9510763164683875,
                    1.119373619601522,
                    3.065887997897676,
                    2.310742720291557,
                    0.7703239556969739
                ],
                "fbest": -0.2303433200653009,
                "evals_best": 9599,
                "evaluations": 9600,
                "iterations": 800,
                "xfavorite": [
                    2.434460756969721,
                    0.2507634368627643,
                    3.1216840125008636,
                    2.4935468896606023,
                    6.000257120554802,
                    -2.4974077823410354,
                    2.05055396283076,
                    14.68496715952667,
                    12.530224308136733,
                    -0.17518198961451972,
                    1.1659456335448848,
                    1.1677284335688864,
                    2.700469414617844,
                    -0.15735340575844423,
                    1.9412624053904413,
                    2.962576463065804,
                    1.124309887908909,
                    3.0627287831707046,
                    2.3175526075221247,
                    0.7637978875914813
                ],
                "stds": [
                    0.05791965450317284,
                    0.07582878668613398,
                    0.04378537593265237,
                    0.0620508778452329,
                    0.08585197755835597,
                    0.03844358726409642,
                    0.06317172991410103,
                    0.1589581119241395,
                    0.15988827422323684,
                    0.024112519278601998,
                    0.010021522123884938,
                    0.01013696446976017,
                    0.0104369718400268,
                    0.011045222928157652,
                    0.013968002165883293,
                    0.013420635952975294,
                    0.00974489937325429,
                    0.003614095370926768,
                    0.027727747554292893,
                    0.02737620663983228
                ],
                "stop": {
                    "maxiter": 800
                }
            },
            "objective_values": [
                -11237.753406447728,
                -8406.288945615772
            ],
            "result_with_budget": [
                {
                    "portfolio": {
                        "AXP": 6,
                        "TRV": 15
                    },
                    "budget": 5369.312026977539,
                    "difference": -15.312026977539062
                },
                {
                    "portfolio": {
                        "AXP": 7,
                        "TRV": 13
                    },
                    "budget": 5184.609146118164,
                    "difference": 169.39085388183594
                }
            ]
        }
    }
}