{
    "84": {
        "hyperparams": {
            "stocks": [
                "GS",
                "MCD"
            ],
            "start": "2015-01-01",
            "end": "2025-01-01",
            "risk_aversion": 0.1,
            "n_qubits": 7,
            "budget": 4467,
            "log_encoding": true,
            "layers": 7,
            "prices_now": {
                "GS": 569.7945556640625,
                "MCD": 288.22589111328125
            },
            "assets_to_qubits": {
                "GS": [
                    0,
                    1,
                    2
                ],
                "MCD": [
                    3,
                    4,
                    5,
                    6
                ]
            },
            "optimizer": "CMAES",
            "lambda_budget": 0.1
        },
        "continuous_variables_solution": {
            "weights": {
                "GS": 0.7518344287953961,
                "MCD": 0.24816557120460392
            },
            "allocation": {
                "GS": 6,
                "MCD": 3
            },
            "value": -239.0215980487001,
            "left_overs": 183.55499200713348
        },
        "continuous_variables_solution_unconstrained": {
            "weights": {
                "GS": 0.7510312932777368,
                "MCD": 0.24803402909924951
            },
            "allocation": {
                "GS": 6,
                "MCD": 3
            },
            "value": -239.0215980487001,
            "left_overs": 183.5549921596221
        },
        "exact_solution": {
            "smallest_eigenvalues": [
                -0.6085574618481212
            ],
            "smallest_bitstrings": [
                "1110100"
            ],
            "first_excited_energy": -0.608511033778572,
            "optimized_portfolio": [
                {
                    "GS": 7,
                    "MCD": 2
                }
            ],
            "second_optimized_portfolio": [
                {
                    "GS": 6,
                    "MCD": 4
                }
            ],
            "spectrum": [
                7.687761026530676e-17,
                -0.46632396568768736,
                -0.2737259973614831,
                -0.5777581659270081,
                -0.1470027225935318,
                -0.532189724483039,
                -0.3801676464602572,
                -0.603021006741721,
                -0.0760362157831201,
                -0.5017935516728006,
                -0.3294822208581238,
                -0.5929283637412702,
                -0.21289939129690083,
                -0.5575115918047845,
                -0.4257817634439071,
                -0.6080348210250998,
                -0.46280493918866467,
                -0.6083925464037305,
                -0.5761705310761189,
                -0.5594231327837964,
                -0.5296286454022464,
                -0.5940607129605431,
                -0.602426904199673,
                -0.5044700084286051,
                -0.4987518487356379,
                -0.6037642953069078,
                -0.5918346970807309,
                -0.5344866855921944,
                -0.555435010783281,
                -0.5792807177801407,
                -0.607946452438094,
                -0.469371638118895,
                -0.2710285656260038,
                -0.5769867204838458,
                -0.46457510705115684,
                -0.6082216102044169,
                -0.3779420440792655,
                -0.6027548220147305,
                -0.5309248196145743,
                -0.5933780446915287,
                -0.32702023297824384,
                -0.5924079300177328,
                -0.5002856251902504,
                -0.6033392463067622,
                -0.4237937751592979,
                -0.6080264095257801,
                -0.5564920849647143,
                -0.5783366368200156,
                -0.5753284358785623,
                -0.5605396569411661,
                -0.608511033778572,
                -0.4313603963105948,
                -0.6020615663288653,
                -0.5061053353901156,
                -0.5946723891335666,
                -0.3362942851742114,
                -0.5912302405337878,
                -0.5358607233220575,
                -0.6041280631596724,
                -0.38636820653091725,
                -0.6078220002231467,
                -0.47127231692540955,
                -0.5801432170699651,
                -0.28113707443090347,
                -0.14542078326639046,
                -0.5315623667847238,
                -0.37905720493185585,
                -0.602897501439366,
                -0.27237893258820184,
                -0.5773795644475304,
                -0.4654530439120032,
                -0.6081075159406039,
                -0.2114347423988629,
                -0.5570078914596538,
                -0.42479064798983396,
                -0.6080415999884172,
                -0.32825317738235366,
                -0.592676446117018,
                -0.5010438346566681,
                -0.6030939280749443,
                -0.5289733591893573,
                -0.5943735719979497,
                -0.6022477440673308,
                -0.5052999622594874,
                -0.5757518951757611,
                -0.5599908308565671,
                -0.6084568353117037,
                -0.4302907902200726,
                -0.5548977682832723,
                -0.5797201409834358,
                -0.6078884484283213,
                -0.4703358597926182,
                -0.5915353741438941,
                -0.5351845127151247,
                -0.6039521574049069,
                -0.38516324304999444,
                -0.37682330766820554,
                -0.6025968496623226,
                -0.5302795954527036,
                -0.5937302462433843,
                -0.46369198322806543,
                -0.6083152856338829,
                -0.5765828308732646,
                -0.5588323125876937,
                -0.42279263089661606,
                -0.6079934730102969,
                -0.555967026978679,
                -0.5788210395035153,
                -0.49952109357506164,
                -0.6035612532663079,
                -0.5921263544593267,
                -0.5337626496395016,
                -0.6018700066708661,
                -0.5068905009358708,
                -0.5949601687683811,
                -0.337604065783563,
                -0.6085574618481212,
                -0.432403891835658,
                -0.5610732997957765,
                -0.22248008970944178,
                -0.6077490856877581,
                -0.4721857248112475,
                -0.5805532926193103,
                -0.28258333943952135,
                -0.6042946747935886,
                -0.3875437784714508,
                -0.5365193483497704,
                -0.1572927114660302
            ],
            "result_with_budget": [
                {
                    "portfolio": {
                        "GS": 7,
                        "MCD": 2
                    },
                    "budget": 4565.013671875,
                    "difference": -98.013671875,
                    "objective_value": -224.22028733614397
                }
            ],
            "result_with_budget_excited": [
                {
                    "portfolio": {
                        "GS": 6,
                        "MCD": 4
                    },
                    "budget": 4571.6708984375,
                    "difference": -104.6708984375,
                    "objective_value": -395.72906998686176
                }
            ]
        },
        "qaoa_solution": {
            "two_most_probable_states": [
                "0010001",
                "1101110"
            ],
            "final_expectation_value": -0.5923665193141678,
            "params": [
                -4.009382536721092,
                4.51942656289669,
                5.934729199087767,
                5.713290837492449,
                6.365498645366319,
                8.250016262627021,
                13.678144157628882,
                1.7836286604668028,
                2.98864960401388,
                1.205305277008352,
                1.2763907148857871,
                -0.181327926005021,
                3.0529927088210806,
                1.5333202461908502
            ],
            "total_steps": 800,
            "states_probs": [
                0.02295031397909091,
                0.027717050509099693
            ],
            "optimized_portfolios": [
                {
                    "GS": 4,
                    "MCD": 8
                },
                {
                    "GS": 3,
                    "MCD": 7
                }
            ],
            "training_history": {
                "xbest": [
                    -4.009382536721092,
                    4.51942656289669,
                    5.934729199087767,
                    5.713290837492449,
                    6.365498645366319,
                    8.250016262627021,
                    13.678144157628882,
                    1.7836286604668028,
                    2.98864960401388,
                    1.205305277008352,
                    1.2763907148857871,
                    -0.181327926005021,
                    3.0529927088210806,
                    1.5333202461908502
                ],
                "fbest": -0.5923665193141678,
                "evals_best": 8768,
                "evaluations": 8800,
                "iterations": 800,
                "xfavorite": [
                    -4.009763144508655,
                    4.5197410145728725,
                    5.92882774211136,
                    5.716759300395103,
                    6.36772975794437,
                    8.258106391669422,
                    13.64386346327298,
                    1.7833021155454478,
                    2.9886836819404876,
                    1.2050145151344502,
                    1.2762792004262167,
                    -0.18117675375343387,
                    3.053026728844229,
                    1.5333954064291144
                ],
                "stds": [
                    0.008627602712154105,
                    0.06458477516945302,
                    0.04740703970991251,
                    0.008307693519696744,
                    0.009659251860792778,
                    0.010751549663766933,
                    0.031423532320027085,
                    0.0016899285943476334,
                    0.0009303250505062796,
                    0.001361235555064613,
                    0.0005254959947845766,
                    0.0002401479260160936,
                    0.00019082574892012502,
                    0.00012931577463748503
                ],
                "stop": {
                    "maxiter": 800
                }
            },
            "objective_values": [
                -1346.034323477435,
                -694.8999644544556
            ],
            "result_with_budget": [
                {
                    "portfolio": {
                        "GS": 4,
                        "MCD": 8
                    },
                    "budget": 4584.9853515625,
                    "difference": -117.9853515625
                },
                {
                    "portfolio": {
                        "GS": 3,
                        "MCD": 7
                    },
                    "budget": 3726.9649047851562,
                    "difference": 740.0350952148438
                }
            ]
        }
    }
}