{
    "84": {
        "hyperparams": {
            "stocks": [
                "GS",
                "MCD"
            ],
            "start": "2015-01-01",
            "end": "2025-01-01",
            "risk_aversion": 0.1,
            "n_qubits": 7,
            "budget": 4467,
            "log_encoding": true,
            "layers": 7,
            "prices_now": {
                "GS": 569.7945556640625,
                "MCD": 288.22589111328125
            },
            "assets_to_qubits": {
                "GS": [
                    0,
                    1,
                    2
                ],
                "MCD": [
                    3,
                    4,
                    5,
                    6
                ]
            },
            "optimizer": "CG"
        },
        "continuous_variables_solution": {
            "weights": {
                "GS": 0.7518336092115817,
                "MCD": 0.2481663907884183
            },
            "allocation": {
                "GS": 6,
                "MCD": 3
            },
            "value": -239.02137875712745,
            "left_overs": 183.55499200722716
        },
        "continuous_variables_solution_unconstrained": {
            "weights": {
                "GS": 0.7510304795048803,
                "MCD": 0.24803483750244737
            },
            "allocation": {
                "GS": 6,
                "MCD": 3
            },
            "value": -239.02137875712745,
            "left_overs": 183.55499215923828
        },
        "qaoa_solution": {
            "two_most_probable_states": [
                "1101110",
                "0010001"
            ],
            "final_expectation_value": -0.5946916055702071,
            "params": [
                6.562363578484441,
                -1.7845394836511619,
                13.35587972622289,
                7.578413439347663,
                9.68639591525074,
                9.568283208519148,
                9.682852416565645,
                0.3632577238988988,
                2.3995611351250306,
                1.4960306974402444,
                3.1061053486290553,
                -0.022243459143792183,
                3.126065983547691,
                1.555251757484147
            ],
            "total_steps": 2037,
            "states_probs": [
                0.026401696008522754,
                0.03077278135007318
            ],
            "optimized_portfolios": [
                {
                    "GS": 3,
                    "MCD": 7
                },
                {
                    "GS": 4,
                    "MCD": 8
                }
            ],
            "training_history": {
                "iterations": 2037,
                "evaluations": 48451,
                "final_value": -0.5946916055702071,
                "success": true,
                "status": 0,
                "message": "Optimization terminated successfully.",
                "execution_time": 15582.11332821846,
                "optimizer": "CG"
            },
            "objective_values": [
                -694.899596204726,
                -1346.0334826727553
            ],
            "result_with_budget": [
                {
                    "portfolio": {
                        "GS": 3,
                        "MCD": 7
                    },
                    "budget": 3726.9649047851562,
                    "difference": 740.0350952148438
                },
                {
                    "portfolio": {
                        "GS": 4,
                        "MCD": 8
                    },
                    "budget": 4584.9853515625,
                    "difference": -117.9853515625
                }
            ]
        }
    }
}